{"coreferences": [{"mentions": [{"head": 1, "animacy": "ANIMATE", "end": 2, "sentence": 1, "text": "We", "number": "PLURAL", "mention_type": "PRONOMINAL", "representativeness": 1, "start": 1, "coref_cluster_id": 1, "mention_id": 1, "gender": "UNKNOWN", "position": {"sent_num": 1, "mention_num": 1}, "is_representative": true}, {"head": 2, "animacy": "ANIMATE", "end": 3, "sentence": 1, "text": "we", "number": "PLURAL", "mention_type": "PRONOMINAL", "representativeness": 1, "start": 2, "coref_cluster_id": 1, "mention_id": 2, "gender": "UNKNOWN", "position": {"sent_num": 1, "mention_num": 2}, "is_representative": false}, {"head": 7, "animacy": "ANIMATE", "end": 8, "sentence": 1, "text": "we", "number": "PLURAL", "mention_type": "PRONOMINAL", "representativeness": 1, "start": 7, "coref_cluster_id": 1, "mention_id": 3, "gender": "UNKNOWN", "position": {"sent_num": 1, "mention_num": 3}, "is_representative": false}, {"head": 25, "animacy": "ANIMATE", "end": 26, "sentence": 2, "text": "we", "number": "PLURAL", "mention_type": "PRONOMINAL", "representativeness": 1, "start": 25, "coref_cluster_id": 1, "mention_id": 13, "gender": "UNKNOWN", "position": {"sent_num": 2, "mention_num": 9}, "is_representative": false}, {"head": 37, "animacy": "ANIMATE", "end": 38, "sentence": 2, "text": "we", "number": "PLURAL", "mention_type": "PRONOMINAL", "representativeness": 1, "start": 37, "coref_cluster_id": 1, "mention_id": 17, "gender": "UNKNOWN", "position": {"sent_num": 2, "mention_num": 13}, "is_representative": false}], "id": 1}, {"mentions": [{"head": 45, "animacy": "ANIMATE", "end": 46, "sentence": 2, "text": "he", "number": "SINGULAR", "mention_type": "PRONOMINAL", "representativeness": 1, "start": 45, "coref_cluster_id": 18, "mention_id": 18, "gender": "MALE", "position": {"sent_num": 2, "mention_num": 14}, "is_representative": true}], "id": 18}, {"mentions": [{"head": 51, "animacy": "INANIMATE", "end": 54, "sentence": 2, "text": "the name this one", "number": "SINGULAR", "mention_type": "NOMINAL", "representativeness": 3, "start": 50, "coref_cluster_id": 19, "mention_id": 19, "gender": "UNKNOWN", "position": {"sent_num": 2, "mention_num": 15}, "is_representative": true}], "id": 19}, {"mentions": [{"head": 11, "animacy": "INANIMATE", "end": 12, "sentence": 1, "text": "this yesterday", "number": "SINGULAR", "mention_type": "PROPER", "representativeness": 4, "start": 10, "coref_cluster_id": 4, "mention_id": 4, "gender": "UNKNOWN", "position": {"sent_num": 1, "mention_num": 4}, "is_representative": true}, {"head": 19, "animacy": "INANIMATE", "end": 20, "sentence": 2, "text": "this yesterday", "number": "SINGULAR", "mention_type": "PROPER", "representativeness": 4, "start": 18, "coref_cluster_id": 4, "mention_id": 11, "gender": "UNKNOWN", "position": {"sent_num": 2, "mention_num": 7}, "is_representative": false}, {"head": 30, "animacy": "INANIMATE", "end": 31, "sentence": 2, "text": "yesterday", "number": "SINGULAR", "mention_type": "PROPER", "representativeness": 4, "start": 30, "coref_cluster_id": 4, "mention_id": 14, "gender": "UNKNOWN", "position": {"sent_num": 2, "mention_num": 10}, "is_representative": false}, {"head": 33, "animacy": "INANIMATE", "end": 34, "sentence": 2, "text": "it", "number": "SINGULAR", "mention_type": "PRONOMINAL", "representativeness": 1, "start": 33, "coref_cluster_id": 4, "mention_id": 15, "gender": "NEUTRAL", "position": {"sent_num": 2, "mention_num": 11}, "is_representative": false}, {"head": 35, "animacy": "INANIMATE", "end": 36, "sentence": 2, "text": "it", "number": "SINGULAR", "mention_type": "PRONOMINAL", "representativeness": 1, "start": 35, "coref_cluster_id": 4, "mention_id": 16, "gender": "NEUTRAL", "position": {"sent_num": 2, "mention_num": 12}, "is_representative": false}], "id": 4}, {"mentions": [{"head": 53, "animacy": "INANIMATE", "end": 54, "sentence": 2, "text": "this one", "number": "SINGULAR", "mention_type": "PROPER", "representativeness": 4, "start": 52, "coref_cluster_id": 20, "mention_id": 20, "gender": "UNKNOWN", "position": {"sent_num": 2, "mention_num": 16}, "is_representative": true}], "id": 20}, {"mentions": [{"head": 4, "animacy": "INANIMATE", "end": 38, "sentence": 2, "text": "this I member anything this was good and this car no car cats no we just did this yesterday but I can that 's we were just in there yesterday went around it was it was we", "number": "SINGULAR", "mention_type": "NOMINAL", "representativeness": 3, "start": 1, "coref_cluster_id": 5, "mention_id": 5, "gender": "NEUTRAL", "position": {"sent_num": 2, "mention_num": 1}, "is_representative": true}], "id": 5}, {"mentions": [{"head": 2, "animacy": "ANIMATE", "end": 3, "sentence": 2, "text": "I", "number": "SINGULAR", "mention_type": "PRONOMINAL", "representativeness": 1, "start": 2, "coref_cluster_id": 6, "mention_id": 6, "gender": "UNKNOWN", "position": {"sent_num": 2, "mention_num": 2}, "is_representative": true}, {"head": 21, "animacy": "ANIMATE", "end": 22, "sentence": 2, "text": "I", "number": "SINGULAR", "mention_type": "PRONOMINAL", "representativeness": 1, "start": 21, "coref_cluster_id": 6, "mention_id": 12, "gender": "UNKNOWN", "position": {"sent_num": 2, "mention_num": 8}, "is_representative": false}], "id": 6}, {"mentions": [{"head": 5, "animacy": "UNKNOWN", "end": 6, "sentence": 2, "text": "this", "number": "UNKNOWN", "mention_type": "NOMINAL", "representativeness": 3, "start": 5, "coref_cluster_id": 7, "mention_id": 7, "gender": "NEUTRAL", "position": {"sent_num": 2, "mention_num": 3}, "is_representative": true}, {"head": 15, "animacy": "ANIMATE", "end": 16, "sentence": 2, "text": "no we", "number": "PLURAL", "mention_type": "PRONOMINAL", "representativeness": 1, "start": 14, "coref_cluster_id": 7, "mention_id": 10, "gender": "UNKNOWN", "position": {"sent_num": 2, "mention_num": 6}, "is_representative": false}], "id": 7}, {"mentions": [{"head": 10, "animacy": "INANIMATE", "end": 36, "sentence": 2, "text": "this car no car cats no we just did this yesterday but I can that 's we were just in there yesterday went around it was it", "number": "SINGULAR", "mention_type": "NOMINAL", "representativeness": 3, "start": 9, "coref_cluster_id": 8, "mention_id": 8, "gender": "NEUTRAL", "position": {"sent_num": 2, "mention_num": 4}, "is_representative": true}], "id": 8}, {"mentions": [{"head": 13, "animacy": "ANIMATE", "end": 34, "sentence": 2, "text": "no car cats no we just did this yesterday but I can that 's we were just in there yesterday went around it", "number": "PLURAL", "mention_type": "NOMINAL", "representativeness": 3, "start": 11, "coref_cluster_id": 9, "mention_id": 9, "gender": "UNKNOWN", "position": {"sent_num": 2, "mention_num": 5}, "is_representative": true}], "id": 9}], "sentences": [{"tokens": [{"index": 0, "word": "We", "character_offset_begin": 0, "character_offset_end": 2, "pos": "PRP", "lemma": "we", "speaker": "PER0", "ner": "O"}, {"index": 1, "word": "we", "character_offset_begin": 3, "character_offset_end": 5, "pos": "PRP", "lemma": "we", "speaker": "PER0", "ner": "O"}, {"index": 2, "word": "went", "character_offset_begin": 6, "character_offset_end": 10, "pos": "VBD", "lemma": "go", "speaker": "PER0", "ner": "O"}, {"index": 3, "word": "there", "character_offset_begin": 11, "character_offset_end": 16, "pos": "RB", "lemma": "there", "speaker": "PER0", "ner": "O"}, {"index": 4, "word": "right", "character_offset_begin": 17, "character_offset_end": 22, "pos": "RB", "lemma": "right", "speaker": "PER0", "ner": "O"}, {"index": 5, "word": "there", "character_offset_begin": 23, "character_offset_end": 28, "pos": "EX", "lemma": "there", "speaker": "PER0", "ner": "O"}, {"index": 6, "word": "we", "character_offset_begin": 29, "character_offset_end": 31, "pos": "PRP", "lemma": "we", "speaker": "PER0", "ner": "O"}, {"index": 7, "word": "just", "character_offset_begin": 32, "character_offset_end": 36, "pos": "RB", "lemma": "just", "speaker": "PER0", "ner": "O"}, {"index": 8, "word": "went", "character_offset_begin": 37, "character_offset_end": 41, "pos": "VBD", "lemma": "go", "speaker": "PER0", "ner": "O"}, {"index": 9, "word": "this", "character_offset_begin": 42, "character_offset_end": 46, "pos": "DT", "lemma": "this", "speaker": "PER0", "ner": "DATE"}, {"index": 10, "word": "yesterday", "character_offset_begin": 47, "character_offset_end": 56, "pos": "NN", "lemma": "yesterday", "speaker": "PER0", "ner": "DATE"}, {"index": 11, "word": ".", "character_offset_begin": 56, "character_offset_end": 57, "pos": ".", "lemma": ".", "speaker": "PER0", "ner": "O"}], "index": 0, "dependencies": [{"target": {"index": 2, "begin_position": 3, "value": "we", "end_position": 5}, "dependent": {"index": 2, "begin_position": 3, "value": "we", "end_position": 5}, "is_extra": false, "governor": {"index": 3, "begin_position": 6, "value": "went", "end_position": 10}, "source": {"index": 3, "begin_position": 6, "value": "went", "end_position": 10}, "relation": {"description": "nominal subject", "value": "nsubj"}}, {"target": {"index": 5, "begin_position": 17, "value": "right", "end_position": 22}, "dependent": {"index": 5, "begin_position": 17, "value": "right", "end_position": 22}, "is_extra": false, "governor": {"index": 3, "begin_position": 6, "value": "went", "end_position": 10}, "source": {"index": 3, "begin_position": 6, "value": "went", "end_position": 10}, "relation": {"description": "adverbial modifier", "value": "advmod"}}, {"target": {"index": 6, "begin_position": 23, "value": "there", "end_position": 28}, "dependent": {"index": 6, "begin_position": 23, "value": "there", "end_position": 28}, "is_extra": false, "governor": {"index": 3, "begin_position": 6, "value": "went", "end_position": 10}, "source": {"index": 3, "begin_position": 6, "value": "went", "end_position": 10}, "relation": {"description": "direct object", "value": "dobj"}}, {"target": {"index": 4, "begin_position": 11, "value": "there", "end_position": 16}, "dependent": {"index": 4, "begin_position": 11, "value": "there", "end_position": 16}, "is_extra": false, "governor": {"index": 5, "begin_position": 17, "value": "right", "end_position": 22}, "source": {"index": 5, "begin_position": 17, "value": "right", "end_position": 22}, "relation": {"description": "adverbial modifier", "value": "advmod"}}, {"target": {"index": 1, "begin_position": 0, "value": "We", "end_position": 2}, "dependent": {"index": 1, "begin_position": 0, "value": "We", "end_position": 2}, "is_extra": false, "governor": {"index": 9, "begin_position": 37, "value": "went", "end_position": 41}, "source": {"index": 9, "begin_position": 37, "value": "went", "end_position": 41}, "relation": {"description": "nominal subject", "value": "nsubj"}}, {"target": {"index": 3, "begin_position": 6, "value": "went", "end_position": 10}, "dependent": {"index": 3, "begin_position": 6, "value": "went", "end_position": 10}, "is_extra": false, "governor": {"index": 9, "begin_position": 37, "value": "went", "end_position": 41}, "source": {"index": 9, "begin_position": 37, "value": "went", "end_position": 41}, "relation": {"description": "parataxis", "value": "parataxis"}}, {"target": {"index": 7, "begin_position": 29, "value": "we", "end_position": 31}, "dependent": {"index": 7, "begin_position": 29, "value": "we", "end_position": 31}, "is_extra": false, "governor": {"index": 9, "begin_position": 37, "value": "went", "end_position": 41}, "source": {"index": 9, "begin_position": 37, "value": "went", "end_position": 41}, "relation": {"description": "nominal subject", "value": "nsubj"}}, {"target": {"index": 8, "begin_position": 32, "value": "just", "end_position": 36}, "dependent": {"index": 8, "begin_position": 32, "value": "just", "end_position": 36}, "is_extra": false, "governor": {"index": 9, "begin_position": 37, "value": "went", "end_position": 41}, "source": {"index": 9, "begin_position": 37, "value": "went", "end_position": 41}, "relation": {"description": "adverbial modifier", "value": "advmod"}}, {"target": {"index": 11, "begin_position": 47, "value": "yesterday", "end_position": 56}, "dependent": {"index": 11, "begin_position": 47, "value": "yesterday", "end_position": 56}, "is_extra": false, "governor": {"index": 9, "begin_position": 37, "value": "went", "end_position": 41}, "source": {"index": 9, "begin_position": 37, "value": "went", "end_position": 41}, "relation": {"description": "temporal modifier", "value": "tmod"}}, {"target": {"index": 10, "begin_position": 42, "value": "this", "end_position": 46}, "dependent": {"index": 10, "begin_position": 42, "value": "this", "end_position": 46}, "is_extra": false, "governor": {"index": 11, "begin_position": 47, "value": "yesterday", "end_position": 56}, "source": {"index": 11, "begin_position": 47, "value": "yesterday", "end_position": 56}, "relation": {"description": "determiner", "value": "det"}}], "phrase_structure": {"category": "ROOT", "constituents": [{"category": "S", "index": 0, "constituents": [{"category": "NP", "index": 0, "constituents": [{"category": "PRP", "index": 0, "constituents": [{"category": "We", "index": 0}]}]}, {"category": "PRN", "index": 1, "constituents": [{"category": "S", "index": 0, "constituents": [{"category": "NP", "index": 0, "constituents": [{"category": "PRP", "index": 0, "constituents": [{"category": "we", "index": 0}]}]}, {"category": "VP", "index": 1, "constituents": [{"category": "VBD", "index": 0, "constituents": [{"category": "went", "index": 0}]}, {"category": "ADVP", "index": 1, "constituents": [{"category": "RB", "index": 0, "constituents": [{"category": "there", "index": 0}]}, {"category": "RB", "index": 1, "constituents": [{"category": "right", "index": 0}]}]}, {"category": "NP", "index": 2, "constituents": [{"category": "EX", "index": 0, "constituents": [{"category": "there", "index": 0}]}]}]}]}]}, {"category": "NP", "index": 2, "constituents": [{"category": "PRP", "index": 0, "constituents": [{"category": "we", "index": 0}]}]}, {"category": "VP", "index": 3, "constituents": [{"category": "ADVP", "index": 0, "constituents": [{"category": "RB", "index": 0, "constituents": [{"category": "just", "index": 0}]}]}, {"category": "VBD", "index": 1, "constituents": [{"category": "went", "index": 0}]}, {"category": "NP-TMP", "index": 2, "constituents": [{"category": "DT", "index": 0, "constituents": [{"category": "this", "index": 0}]}, {"category": "NN", "index": 1, "constituents": [{"category": "yesterday", "index": 0}]}]}]}, {"category": ".", "index": 4, "constituents": [{"category": ".", "index": 0}]}]}]}}, {"tokens": [{"index": 0, "word": "this", "character_offset_begin": 58, "character_offset_end": 62, "pos": "DT", "lemma": "this", "speaker": "PER0", "ner": "O"}, {"index": 1, "word": "I", "character_offset_begin": 63, "character_offset_end": 64, "pos": "PRP", "lemma": "I", "speaker": "PER0", "ner": "O"}, {"index": 2, "word": "member", "character_offset_begin": 65, "character_offset_end": 71, "pos": "NN", "lemma": "member", "speaker": "PER0", "ner": "O"}, {"index": 3, "word": "anything", "character_offset_begin": 72, "character_offset_end": 80, "pos": "NN", "lemma": "anything", "speaker": "PER0", "ner": "O"}, {"index": 4, "word": "this", "character_offset_begin": 81, "character_offset_end": 85, "pos": "DT", "lemma": "this", "speaker": "PER0", "ner": "O"}, {"index": 5, "word": "was", "character_offset_begin": 86, "character_offset_end": 89, "pos": "VBD", "lemma": "be", "speaker": "PER0", "ner": "O"}, {"index": 6, "word": "good", "character_offset_begin": 90, "character_offset_end": 94, "pos": "JJ", "lemma": "good", "speaker": "PER0", "ner": "O"}, {"index": 7, "word": "and", "character_offset_begin": 95, "character_offset_end": 98, "pos": "CC", "lemma": "and", "speaker": "PER0", "ner": "O"}, {"index": 8, "word": "this", "character_offset_begin": 99, "character_offset_end": 103, "pos": "DT", "lemma": "this", "speaker": "PER0", "ner": "O"}, {"index": 9, "word": "car", "character_offset_begin": 104, "character_offset_end": 107, "pos": "NN", "lemma": "car", "speaker": "PER0", "ner": "O"}, {"index": 10, "word": "no", "character_offset_begin": 108, "character_offset_end": 110, "pos": "DT", "lemma": "no", "speaker": "PER0", "ner": "O"}, {"index": 11, "word": "car", "character_offset_begin": 111, "character_offset_end": 114, "pos": "NN", "lemma": "car", "speaker": "PER0", "ner": "O"}, {"index": 12, "word": "cats", "character_offset_begin": 115, "character_offset_end": 119, "pos": "NNS", "lemma": "cat", "speaker": "PER0", "ner": "O"}, {"index": 13, "word": "no", "character_offset_begin": 120, "character_offset_end": 122, "pos": "DT", "lemma": "no", "speaker": "PER0", "ner": "O"}, {"index": 14, "word": "we", "character_offset_begin": 123, "character_offset_end": 125, "pos": "PRP", "lemma": "we", "speaker": "PER0", "ner": "O"}, {"index": 15, "word": "just", "character_offset_begin": 126, "character_offset_end": 130, "pos": "RB", "lemma": "just", "speaker": "PER0", "ner": "O"}, {"index": 16, "word": "did", "character_offset_begin": 131, "character_offset_end": 134, "pos": "VBD", "lemma": "do", "speaker": "PER0", "ner": "O"}, {"index": 17, "word": "this", "character_offset_begin": 135, "character_offset_end": 139, "pos": "DT", "lemma": "this", "speaker": "PER0", "ner": "DATE"}, {"index": 18, "word": "yesterday", "character_offset_begin": 140, "character_offset_end": 149, "pos": "NN", "lemma": "yesterday", "speaker": "PER0", "ner": "DATE"}, {"index": 19, "word": "but", "character_offset_begin": 150, "character_offset_end": 153, "pos": "CC", "lemma": "but", "speaker": "PER0", "ner": "O"}, {"index": 20, "word": "I", "character_offset_begin": 154, "character_offset_end": 155, "pos": "PRP", "lemma": "I", "speaker": "PER0", "ner": "O"}, {"index": 21, "word": "can", "character_offset_begin": 156, "character_offset_end": 159, "pos": "MD", "lemma": "can", "speaker": "PER0", "ner": "O"}, {"index": 22, "word": "that", "character_offset_begin": 160, "character_offset_end": 164, "pos": "WDT", "lemma": "that", "speaker": "PER0", "ner": "O"}, {"index": 23, "word": "'s", "character_offset_begin": 164, "character_offset_end": 166, "pos": "VBZ", "lemma": "be", "speaker": "PER0", "ner": "O"}, {"index": 24, "word": "we", "character_offset_begin": 167, "character_offset_end": 169, "pos": "PRP", "lemma": "we", "speaker": "PER0", "ner": "O"}, {"index": 25, "word": "were", "character_offset_begin": 170, "character_offset_end": 174, "pos": "VBD", "lemma": "be", "speaker": "PER0", "ner": "O"}, {"index": 26, "word": "just", "character_offset_begin": 175, "character_offset_end": 179, "pos": "RB", "lemma": "just", "speaker": "PER0", "ner": "O"}, {"index": 27, "word": "in", "character_offset_begin": 180, "character_offset_end": 182, "pos": "IN", "lemma": "in", "speaker": "PER0", "ner": "O"}, {"index": 28, "word": "there", "character_offset_begin": 183, "character_offset_end": 188, "pos": "EX", "lemma": "there", "speaker": "PER0", "ner": "O"}, {"index": 29, "word": "yesterday", "character_offset_begin": 189, "character_offset_end": 198, "pos": "NN", "lemma": "yesterday", "speaker": "PER0", "ner": "DATE"}, {"index": 30, "word": "went", "character_offset_begin": 199, "character_offset_end": 203, "pos": "VBD", "lemma": "go", "speaker": "PER0", "ner": "O"}, {"index": 31, "word": "around", "character_offset_begin": 204, "character_offset_end": 210, "pos": "IN", "lemma": "around", "speaker": "PER0", "ner": "O"}, {"index": 32, "word": "it", "character_offset_begin": 211, "character_offset_end": 213, "pos": "PRP", "lemma": "it", "speaker": "PER0", "ner": "O"}, {"index": 33, "word": "was", "character_offset_begin": 214, "character_offset_end": 217, "pos": "VBD", "lemma": "be", "speaker": "PER0", "ner": "O"}, {"index": 34, "word": "it", "character_offset_begin": 218, "character_offset_end": 220, "pos": "PRP", "lemma": "it", "speaker": "PER0", "ner": "O"}, {"index": 35, "word": "was", "character_offset_begin": 221, "character_offset_end": 224, "pos": "VBD", "lemma": "be", "speaker": "PER0", "ner": "O"}, {"index": 36, "word": "we", "character_offset_begin": 225, "character_offset_end": 227, "pos": "PRP", "lemma": "we", "speaker": "PER0", "ner": "O"}, {"index": 37, "word": "went", "character_offset_begin": 228, "character_offset_end": 232, "pos": "VBD", "lemma": "go", "speaker": "PER0", "ner": "O"}, {"index": 38, "word": "up", "character_offset_begin": 233, "character_offset_end": 235, "pos": "RB", "lemma": "up", "speaker": "PER0", "ner": "O"}, {"index": 39, "word": "in", "character_offset_begin": 236, "character_offset_end": 238, "pos": "IN", "lemma": "in", "speaker": "PER0", "ner": "O"}, {"index": 40, "word": "there", "character_offset_begin": 239, "character_offset_end": 244, "pos": "EX", "lemma": "there", "speaker": "PER0", "ner": "O"}, {"index": 41, "word": "was", "character_offset_begin": 245, "character_offset_end": 248, "pos": "VBD", "lemma": "be", "speaker": "PER0", "ner": "O"}, {"index": 42, "word": "oh", "character_offset_begin": 249, "character_offset_end": 251, "pos": "UH", "lemma": "oh", "speaker": "PER0", "ner": "O"}, {"index": 43, "word": "forget", "character_offset_begin": 252, "character_offset_end": 258, "pos": "VB", "lemma": "forget", "speaker": "PER0", "ner": "O"}, {"index": 44, "word": "he", "character_offset_begin": 259, "character_offset_end": 261, "pos": "PRP", "lemma": "he", "speaker": "PER0", "ner": "O"}, {"index": 45, "word": "was", "character_offset_begin": 262, "character_offset_end": 265, "pos": "VBD", "lemma": "be", "speaker": "PER0", "ner": "O"}, {"index": 46, "word": "in", "character_offset_begin": 266, "character_offset_end": 268, "pos": "IN", "lemma": "in", "speaker": "PER0", "ner": "O"}, {"index": 47, "word": "that", "character_offset_begin": 269, "character_offset_end": 273, "pos": "DT", "lemma": "that", "speaker": "PER0", "ner": "O"}, {"index": 48, "word": "'s", "character_offset_begin": 273, "character_offset_end": 275, "pos": "VBZ", "lemma": "be", "speaker": "PER0", "ner": "O"}, {"index": 49, "word": "the", "character_offset_begin": 276, "character_offset_end": 279, "pos": "DT", "lemma": "the", "speaker": "PER0", "ner": "O"}, {"index": 50, "word": "name", "character_offset_begin": 280, "character_offset_end": 284, "pos": "NN", "lemma": "name", "speaker": "PER0", "ner": "O"}, {"index": 51, "word": "this", "character_offset_begin": 285, "character_offset_end": 289, "pos": "DT", "lemma": "this", "speaker": "PER0", "ner": "O"}, {"index": 52, "word": "one", "character_offset_begin": 290, "character_offset_end": 293, "pos": "CD", "lemma": "one", "speaker": "PER0", "ner": "NUMBER"}, {"index": 53, "word": "there", "character_offset_begin": 294, "character_offset_end": 299, "pos": "EX", "lemma": "there", "speaker": "PER0", "ner": "O"}], "index": 1, "dependencies": [{"target": {"index": 3, "begin_position": 65, "value": "member", "end_position": 71}, "dependent": {"index": 3, "begin_position": 65, "value": "member", "end_position": 71}, "is_extra": false, "governor": {"index": 4, "begin_position": 72, "value": "anything", "end_position": 80}, "source": {"index": 4, "begin_position": 72, "value": "anything", "end_position": 80}, "relation": {"description": "nn modifier", "value": "nn"}}, {"target": {"index": 36, "begin_position": 221, "value": "was", "end_position": 224}, "dependent": {"index": 36, "begin_position": 221, "value": "was", "end_position": 224}, "is_extra": false, "governor": {"index": 4, "begin_position": 72, "value": "anything", "end_position": 80}, "source": {"index": 4, "begin_position": 72, "value": "anything", "end_position": 80}, "relation": {"description": "relative clause modifier", "value": "rcmod"}}, {"target": {"index": 7, "begin_position": 90, "value": "good", "end_position": 94}, "dependent": {"index": 7, "begin_position": 90, "value": "good", "end_position": 94}, "is_extra": false, "governor": {"index": 4, "begin_position": 72, "value": "anything", "end_position": 80}, "source": {"index": 4, "begin_position": 72, "value": "anything", "end_position": 80}, "relation": {"description": "relative clause modifier", "value": "rcmod"}}, {"target": {"index": 1, "begin_position": 58, "value": "this", "end_position": 62}, "dependent": {"index": 1, "begin_position": 58, "value": "this", "end_position": 62}, "is_extra": false, "governor": {"index": 4, "begin_position": 72, "value": "anything", "end_position": 80}, "source": {"index": 4, "begin_position": 72, "value": "anything", "end_position": 80}, "relation": {"description": "determiner", "value": "det"}}, {"target": {"index": 2, "begin_position": 63, "value": "I", "end_position": 64}, "dependent": {"index": 2, "begin_position": 63, "value": "I", "end_position": 64}, "is_extra": false, "governor": {"index": 4, "begin_position": 72, "value": "anything", "end_position": 80}, "source": {"index": 4, "begin_position": 72, "value": "anything", "end_position": 80}, "relation": {"description": "adjectival modifier", "value": "amod"}}, {"target": {"index": 36, "begin_position": 221, "value": "was", "end_position": 224}, "dependent": {"index": 36, "begin_position": 221, "value": "was", "end_position": 224}, "is_extra": false, "governor": {"index": 7, "begin_position": 90, "value": "good", "end_position": 94}, "source": {"index": 7, "begin_position": 90, "value": "good", "end_position": 94}, "relation": {"description": "conj_collapsed", "value": "conj"}}, {"target": {"index": 5, "begin_position": 81, "value": "this", "end_position": 85}, "dependent": {"index": 5, "begin_position": 81, "value": "this", "end_position": 85}, "is_extra": false, "governor": {"index": 7, "begin_position": 90, "value": "good", "end_position": 94}, "source": {"index": 7, "begin_position": 90, "value": "good", "end_position": 94}, "relation": {"description": "nominal subject", "value": "nsubj"}}, {"target": {"index": 6, "begin_position": 86, "value": "was", "end_position": 89}, "dependent": {"index": 6, "begin_position": 86, "value": "was", "end_position": 89}, "is_extra": false, "governor": {"index": 7, "begin_position": 90, "value": "good", "end_position": 94}, "source": {"index": 7, "begin_position": 90, "value": "good", "end_position": 94}, "relation": {"description": "copula", "value": "cop"}}, {"target": {"index": 9, "begin_position": 99, "value": "this", "end_position": 103}, "dependent": {"index": 9, "begin_position": 99, "value": "this", "end_position": 103}, "is_extra": false, "governor": {"index": 10, "begin_position": 104, "value": "car", "end_position": 107}, "source": {"index": 10, "begin_position": 104, "value": "car", "end_position": 107}, "relation": {"description": "determiner", "value": "det"}}, {"target": {"index": 34, "begin_position": 214, "value": "was", "end_position": 217}, "dependent": {"index": 34, "begin_position": 214, "value": "was", "end_position": 217}, "is_extra": false, "governor": {"index": 10, "begin_position": 104, "value": "car", "end_position": 107}, "source": {"index": 10, "begin_position": 104, "value": "car", "end_position": 107}, "relation": {"description": "relative clause modifier", "value": "rcmod"}}, {"target": {"index": 24, "begin_position": 164, "value": "'s", "end_position": 166}, "dependent": {"index": 24, "begin_position": 164, "value": "'s", "end_position": 166}, "is_extra": false, "governor": {"index": 13, "begin_position": 115, "value": "cats", "end_position": 119}, "source": {"index": 13, "begin_position": 115, "value": "cats", "end_position": 119}, "relation": {"description": "relative clause modifier", "value": "rcmod"}}, {"target": {"index": 11, "begin_position": 108, "value": "no", "end_position": 110}, "dependent": {"index": 11, "begin_position": 108, "value": "no", "end_position": 110}, "is_extra": false, "governor": {"index": 13, "begin_position": 115, "value": "cats", "end_position": 119}, "source": {"index": 13, "begin_position": 115, "value": "cats", "end_position": 119}, "relation": {"description": "negation modifier", "value": "neg"}}, {"target": {"index": 12, "begin_position": 111, "value": "car", "end_position": 114}, "dependent": {"index": 12, "begin_position": 111, "value": "car", "end_position": 114}, "is_extra": false, "governor": {"index": 13, "begin_position": 115, "value": "cats", "end_position": 119}, "source": {"index": 13, "begin_position": 115, "value": "cats", "end_position": 119}, "relation": {"description": "nn modifier", "value": "nn"}}, {"target": {"index": 17, "begin_position": 131, "value": "did", "end_position": 134}, "dependent": {"index": 17, "begin_position": 131, "value": "did", "end_position": 134}, "is_extra": false, "governor": {"index": 13, "begin_position": 115, "value": "cats", "end_position": 119}, "source": {"index": 13, "begin_position": 115, "value": "cats", "end_position": 119}, "relation": {"description": "relative clause modifier", "value": "rcmod"}}, {"target": {"index": 14, "begin_position": 120, "value": "no", "end_position": 122}, "dependent": {"index": 14, "begin_position": 120, "value": "no", "end_position": 122}, "is_extra": false, "governor": {"index": 15, "begin_position": 123, "value": "we", "end_position": 125}, "source": {"index": 15, "begin_position": 123, "value": "we", "end_position": 125}, "relation": {"description": "negation modifier", "value": "neg"}}, {"target": {"index": 19, "begin_position": 140, "value": "yesterday", "end_position": 149}, "dependent": {"index": 19, "begin_position": 140, "value": "yesterday", "end_position": 149}, "is_extra": false, "governor": {"index": 17, "begin_position": 131, "value": "did", "end_position": 134}, "source": {"index": 17, "begin_position": 131, "value": "did", "end_position": 134}, "relation": {"description": "temporal modifier", "value": "tmod"}}, {"target": {"index": 22, "begin_position": 156, "value": "can", "end_position": 159}, "dependent": {"index": 22, "begin_position": 156, "value": "can", "end_position": 159}, "is_extra": false, "governor": {"index": 17, "begin_position": 131, "value": "did", "end_position": 134}, "source": {"index": 17, "begin_position": 131, "value": "did", "end_position": 134}, "relation": {"description": "clausal complement", "value": "ccomp"}}, {"target": {"index": 15, "begin_position": 123, "value": "we", "end_position": 125}, "dependent": {"index": 15, "begin_position": 123, "value": "we", "end_position": 125}, "is_extra": false, "governor": {"index": 17, "begin_position": 131, "value": "did", "end_position": 134}, "source": {"index": 17, "begin_position": 131, "value": "did", "end_position": 134}, "relation": {"description": "nominal subject", "value": "nsubj"}}, {"target": {"index": 16, "begin_position": 126, "value": "just", "end_position": 130}, "dependent": {"index": 16, "begin_position": 126, "value": "just", "end_position": 130}, "is_extra": false, "governor": {"index": 17, "begin_position": 131, "value": "did", "end_position": 134}, "source": {"index": 17, "begin_position": 131, "value": "did", "end_position": 134}, "relation": {"description": "adverbial modifier", "value": "advmod"}}, {"target": {"index": 18, "begin_position": 135, "value": "this", "end_position": 139}, "dependent": {"index": 18, "begin_position": 135, "value": "this", "end_position": 139}, "is_extra": false, "governor": {"index": 19, "begin_position": 140, "value": "yesterday", "end_position": 149}, "source": {"index": 19, "begin_position": 140, "value": "yesterday", "end_position": 149}, "relation": {"description": "determiner", "value": "det"}}, {"target": {"index": 20, "begin_position": 150, "value": "but", "end_position": 153}, "dependent": {"index": 20, "begin_position": 150, "value": "but", "end_position": 153}, "is_extra": false, "governor": {"index": 22, "begin_position": 156, "value": "can", "end_position": 159}, "source": {"index": 22, "begin_position": 156, "value": "can", "end_position": 159}, "relation": {"description": "coordination", "value": "cc"}}, {"target": {"index": 21, "begin_position": 154, "value": "I", "end_position": 155}, "dependent": {"index": 21, "begin_position": 154, "value": "I", "end_position": 155}, "is_extra": false, "governor": {"index": 22, "begin_position": 156, "value": "can", "end_position": 159}, "source": {"index": 22, "begin_position": 156, "value": "can", "end_position": 159}, "relation": {"description": "nominal subject", "value": "nsubj"}}, {"target": {"index": 23, "begin_position": 160, "value": "that", "end_position": 164}, "dependent": {"index": 23, "begin_position": 160, "value": "that", "end_position": 164}, "is_extra": false, "governor": {"index": 24, "begin_position": 164, "value": "'s", "end_position": 166}, "source": {"index": 24, "begin_position": 164, "value": "'s", "end_position": 166}, "relation": {"description": "nominal subject", "value": "nsubj"}}, {"target": {"index": 26, "begin_position": 170, "value": "were", "end_position": 174}, "dependent": {"index": 26, "begin_position": 170, "value": "were", "end_position": 174}, "is_extra": false, "governor": {"index": 24, "begin_position": 164, "value": "'s", "end_position": 166}, "source": {"index": 24, "begin_position": 164, "value": "'s", "end_position": 166}, "relation": {"description": "clausal complement", "value": "ccomp"}}, {"target": {"index": 25, "begin_position": 167, "value": "we", "end_position": 169}, "dependent": {"index": 25, "begin_position": 167, "value": "we", "end_position": 169}, "is_extra": false, "governor": {"index": 26, "begin_position": 170, "value": "were", "end_position": 174}, "source": {"index": 26, "begin_position": 170, "value": "were", "end_position": 174}, "relation": {"description": "nominal subject", "value": "nsubj"}}, {"target": {"index": 31, "begin_position": 199, "value": "went", "end_position": 203}, "dependent": {"index": 31, "begin_position": 199, "value": "went", "end_position": 203}, "is_extra": false, "governor": {"index": 26, "begin_position": 170, "value": "were", "end_position": 174}, "source": {"index": 26, "begin_position": 170, "value": "were", "end_position": 174}, "relation": {"description": "adverbial clause modifier", "value": "advcl"}}, {"target": {"index": 27, "begin_position": 175, "value": "just", "end_position": 179}, "dependent": {"index": 27, "begin_position": 175, "value": "just", "end_position": 179}, "is_extra": false, "governor": {"index": 31, "begin_position": 199, "value": "went", "end_position": 203}, "source": {"index": 31, "begin_position": 199, "value": "went", "end_position": 203}, "relation": {"description": "adverbial modifier", "value": "advmod"}}, {"target": {"index": 28, "begin_position": 180, "value": "in", "end_position": 182}, "dependent": {"index": 28, "begin_position": 180, "value": "in", "end_position": 182}, "is_extra": false, "governor": {"index": 31, "begin_position": 199, "value": "went", "end_position": 203}, "source": {"index": 31, "begin_position": 199, "value": "went", "end_position": 203}, "relation": {"description": "marker", "value": "mark"}}, {"target": {"index": 29, "begin_position": 183, "value": "there", "end_position": 188}, "dependent": {"index": 29, "begin_position": 183, "value": "there", "end_position": 188}, "is_extra": false, "governor": {"index": 31, "begin_position": 199, "value": "went", "end_position": 203}, "source": {"index": 31, "begin_position": 199, "value": "went", "end_position": 203}, "relation": {"description": "expletive", "value": "expl"}}, {"target": {"index": 30, "begin_position": 189, "value": "yesterday", "end_position": 198}, "dependent": {"index": 30, "begin_position": 189, "value": "yesterday", "end_position": 198}, "is_extra": false, "governor": {"index": 31, "begin_position": 199, "value": "went", "end_position": 203}, "source": {"index": 31, "begin_position": 199, "value": "went", "end_position": 203}, "relation": {"description": "temporal modifier", "value": "tmod"}}, {"target": {"index": 33, "begin_position": 211, "value": "it", "end_position": 213}, "dependent": {"index": 33, "begin_position": 211, "value": "it", "end_position": 213}, "is_extra": false, "governor": {"index": 31, "begin_position": 199, "value": "went", "end_position": 203}, "source": {"index": 31, "begin_position": 199, "value": "went", "end_position": 203}, "relation": {"description": "prep_collapsed", "value": "prep"}}, {"target": {"index": 35, "begin_position": 218, "value": "it", "end_position": 220}, "dependent": {"index": 35, "begin_position": 218, "value": "it", "end_position": 220}, "is_extra": false, "governor": {"index": 34, "begin_position": 214, "value": "was", "end_position": 217}, "source": {"index": 34, "begin_position": 214, "value": "was", "end_position": 217}, "relation": {"description": "dependent", "value": "dep"}}, {"target": {"index": 13, "begin_position": 115, "value": "cats", "end_position": 119}, "dependent": {"index": 13, "begin_position": 115, "value": "cats", "end_position": 119}, "is_extra": false, "governor": {"index": 34, "begin_position": 214, "value": "was", "end_position": 217}, "source": {"index": 34, "begin_position": 214, "value": "was", "end_position": 217}, "relation": {"description": "nominal subject", "value": "nsubj"}}, {"target": {"index": 37, "begin_position": 225, "value": "we", "end_position": 227}, "dependent": {"index": 37, "begin_position": 225, "value": "we", "end_position": 227}, "is_extra": false, "governor": {"index": 36, "begin_position": 221, "value": "was", "end_position": 224}, "source": {"index": 36, "begin_position": 221, "value": "was", "end_position": 224}, "relation": {"description": "dependent", "value": "dep"}}, {"target": {"index": 10, "begin_position": 104, "value": "car", "end_position": 107}, "dependent": {"index": 10, "begin_position": 104, "value": "car", "end_position": 107}, "is_extra": false, "governor": {"index": 36, "begin_position": 221, "value": "was", "end_position": 224}, "source": {"index": 36, "begin_position": 221, "value": "was", "end_position": 224}, "relation": {"description": "nominal subject", "value": "nsubj"}}, {"target": {"index": 4, "begin_position": 72, "value": "anything", "end_position": 80}, "dependent": {"index": 4, "begin_position": 72, "value": "anything", "end_position": 80}, "is_extra": false, "governor": {"index": 38, "begin_position": 228, "value": "went", "end_position": 232}, "source": {"index": 38, "begin_position": 228, "value": "went", "end_position": 232}, "relation": {"description": "nominal subject", "value": "nsubj"}}, {"target": {"index": 39, "begin_position": 233, "value": "up", "end_position": 235}, "dependent": {"index": 39, "begin_position": 233, "value": "up", "end_position": 235}, "is_extra": false, "governor": {"index": 38, "begin_position": 228, "value": "went", "end_position": 232}, "source": {"index": 38, "begin_position": 228, "value": "went", "end_position": 232}, "relation": {"description": "adverbial modifier", "value": "advmod"}}, {"target": {"index": 42, "begin_position": 245, "value": "was", "end_position": 248}, "dependent": {"index": 42, "begin_position": 245, "value": "was", "end_position": 248}, "is_extra": false, "governor": {"index": 38, "begin_position": 228, "value": "went", "end_position": 232}, "source": {"index": 38, "begin_position": 228, "value": "went", "end_position": 232}, "relation": {"description": "adverbial clause modifier", "value": "advcl"}}, {"target": {"index": 40, "begin_position": 236, "value": "in", "end_position": 238}, "dependent": {"index": 40, "begin_position": 236, "value": "in", "end_position": 238}, "is_extra": false, "governor": {"index": 42, "begin_position": 245, "value": "was", "end_position": 248}, "source": {"index": 42, "begin_position": 245, "value": "was", "end_position": 248}, "relation": {"description": "marker", "value": "mark"}}, {"target": {"index": 41, "begin_position": 239, "value": "there", "end_position": 244}, "dependent": {"index": 41, "begin_position": 239, "value": "there", "end_position": 244}, "is_extra": false, "governor": {"index": 42, "begin_position": 245, "value": "was", "end_position": 248}, "source": {"index": 42, "begin_position": 245, "value": "was", "end_position": 248}, "relation": {"description": "expletive", "value": "expl"}}, {"target": {"index": 44, "begin_position": 252, "value": "forget", "end_position": 258}, "dependent": {"index": 44, "begin_position": 252, "value": "forget", "end_position": 258}, "is_extra": false, "governor": {"index": 42, "begin_position": 245, "value": "was", "end_position": 248}, "source": {"index": 42, "begin_position": 245, "value": "was", "end_position": 248}, "relation": {"description": "clausal complement", "value": "ccomp"}}, {"target": {"index": 43, "begin_position": 249, "value": "oh", "end_position": 251}, "dependent": {"index": 43, "begin_position": 249, "value": "oh", "end_position": 251}, "is_extra": false, "governor": {"index": 44, "begin_position": 252, "value": "forget", "end_position": 258}, "source": {"index": 44, "begin_position": 252, "value": "forget", "end_position": 258}, "relation": {"description": "discourse element", "value": "discourse"}}, {"target": {"index": 46, "begin_position": 262, "value": "was", "end_position": 265}, "dependent": {"index": 46, "begin_position": 262, "value": "was", "end_position": 265}, "is_extra": false, "governor": {"index": 44, "begin_position": 252, "value": "forget", "end_position": 258}, "source": {"index": 44, "begin_position": 252, "value": "forget", "end_position": 258}, "relation": {"description": "clausal complement", "value": "ccomp"}}, {"target": {"index": 51, "begin_position": 280, "value": "name", "end_position": 284}, "dependent": {"index": 51, "begin_position": 280, "value": "name", "end_position": 284}, "is_extra": false, "governor": {"index": 46, "begin_position": 262, "value": "was", "end_position": 265}, "source": {"index": 46, "begin_position": 262, "value": "was", "end_position": 265}, "relation": {"description": "prepc_collapsed", "value": "prepc"}}, {"target": {"index": 45, "begin_position": 259, "value": "he", "end_position": 261}, "dependent": {"index": 45, "begin_position": 259, "value": "he", "end_position": 261}, "is_extra": false, "governor": {"index": 46, "begin_position": 262, "value": "was", "end_position": 265}, "source": {"index": 46, "begin_position": 262, "value": "was", "end_position": 265}, "relation": {"description": "nominal subject", "value": "nsubj"}}, {"target": {"index": 53, "begin_position": 290, "value": "one", "end_position": 293}, "dependent": {"index": 53, "begin_position": 290, "value": "one", "end_position": 293}, "is_extra": false, "governor": {"index": 51, "begin_position": 280, "value": "name", "end_position": 284}, "source": {"index": 51, "begin_position": 280, "value": "name", "end_position": 284}, "relation": {"description": "dependent", "value": "dep"}}, {"target": {"index": 54, "begin_position": 294, "value": "there", "end_position": 299}, "dependent": {"index": 54, "begin_position": 294, "value": "there", "end_position": 299}, "is_extra": false, "governor": {"index": 51, "begin_position": 280, "value": "name", "end_position": 284}, "source": {"index": 51, "begin_position": 280, "value": "name", "end_position": 284}, "relation": {"description": "expletive", "value": "expl"}}, {"target": {"index": 48, "begin_position": 269, "value": "that", "end_position": 273}, "dependent": {"index": 48, "begin_position": 269, "value": "that", "end_position": 273}, "is_extra": false, "governor": {"index": 51, "begin_position": 280, "value": "name", "end_position": 284}, "source": {"index": 51, "begin_position": 280, "value": "name", "end_position": 284}, "relation": {"description": "direct object", "value": "dobj"}}, {"target": {"index": 49, "begin_position": 273, "value": "'s", "end_position": 275}, "dependent": {"index": 49, "begin_position": 273, "value": "'s", "end_position": 275}, "is_extra": false, "governor": {"index": 51, "begin_position": 280, "value": "name", "end_position": 284}, "source": {"index": 51, "begin_position": 280, "value": "name", "end_position": 284}, "relation": {"description": "copula", "value": "cop"}}, {"target": {"index": 50, "begin_position": 276, "value": "the", "end_position": 279}, "dependent": {"index": 50, "begin_position": 276, "value": "the", "end_position": 279}, "is_extra": false, "governor": {"index": 51, "begin_position": 280, "value": "name", "end_position": 284}, "source": {"index": 51, "begin_position": 280, "value": "name", "end_position": 284}, "relation": {"description": "determiner", "value": "det"}}, {"target": {"index": 52, "begin_position": 285, "value": "this", "end_position": 289}, "dependent": {"index": 52, "begin_position": 285, "value": "this", "end_position": 289}, "is_extra": false, "governor": {"index": 53, "begin_position": 290, "value": "one", "end_position": 293}, "source": {"index": 53, "begin_position": 290, "value": "one", "end_position": 293}, "relation": {"description": "determiner", "value": "det"}}], "phrase_structure": {"category": "ROOT", "constituents": [{"category": "S", "index": 0, "constituents": [{"category": "NP", "index": 0, "constituents": [{"category": "NP", "index": 0, "constituents": [{"category": "DT", "index": 0, "constituents": [{"category": "this", "index": 0}]}, {"category": "ADJP", "index": 1, "constituents": [{"category": "NP", "index": 0, "constituents": [{"category": "PRP", "index": 0, "constituents": [{"category": "I", "index": 0}]}]}]}, {"category": "NN", "index": 2, "constituents": [{"category": "member", "index": 0}]}, {"category": "NN", "index": 3, "constituents": [{"category": "anything", "index": 0}]}]}, {"category": "SBAR", "index": 1, "constituents": [{"category": "S", "index": 0, "constituents": [{"category": "S", "index": 0, "constituents": [{"category": "NP", "index": 0, "constituents": [{"category": "DT", "index": 0, "constituents": [{"category": "this", "index": 0}]}]}, {"category": "VP", "index": 1, "constituents": [{"category": "VBD", "index": 0, "constituents": [{"category": "was", "index": 0}]}, {"category": "ADJP", "index": 1, "constituents": [{"category": "JJ", "index": 0, "constituents": [{"category": "good", "index": 0}]}]}]}]}, {"category": "CC", "index": 1, "constituents": [{"category": "and", "index": 0}]}, {"category": "S", "index": 2, "constituents": [{"category": "NP", "index": 0, "constituents": [{"category": "NP", "index": 0, "constituents": [{"category": "DT", "index": 0, "constituents": [{"category": "this", "index": 0}]}, {"category": "NN", "index": 1, "constituents": [{"category": "car", "index": 0}]}]}, {"category": "SBAR", "index": 1, "constituents": [{"category": "S", "index": 0, "constituents": [{"category": "NP", "index": 0, "constituents": [{"category": "NP", "index": 0, "constituents": [{"category": "DT", "index": 0, "constituents": [{"category": "no", "index": 0}]}, {"category": "NN", "index": 1, "constituents": [{"category": "car", "index": 0}]}, {"category": "NNS", "index": 2, "constituents": [{"category": "cats", "index": 0}]}]}, {"category": "SBAR", "index": 1, "constituents": [{"category": "S", "index": 0, "constituents": [{"category": "NP", "index": 0, "constituents": [{"category": "DT", "index": 0, "constituents": [{"category": "no", "index": 0}]}, {"category": "PRP", "index": 1, "constituents": [{"category": "we", "index": 0}]}]}, {"category": "ADVP", "index": 1, "constituents": [{"category": "RB", "index": 0, "constituents": [{"category": "just", "index": 0}]}]}, {"category": "VP", "index": 2, "constituents": [{"category": "VBD", "index": 0, "constituents": [{"category": "did", "index": 0}]}, {"category": "NP-TMP", "index": 1, "constituents": [{"category": "DT", "index": 0, "constituents": [{"category": "this", "index": 0}]}, {"category": "NN", "index": 1, "constituents": [{"category": "yesterday", "index": 0}]}]}, {"category": "SBAR", "index": 2, "constituents": [{"category": "CC", "index": 0, "constituents": [{"category": "but", "index": 0}]}, {"category": "S", "index": 1, "constituents": [{"category": "NP", "index": 0, "constituents": [{"category": "PRP", "index": 0, "constituents": [{"category": "I", "index": 0}]}]}, {"category": "VP", "index": 1, "constituents": [{"category": "MD", "index": 0, "constituents": [{"category": "can", "index": 0}]}]}]}]}]}]}]}, {"category": "SBAR", "index": 2, "constituents": [{"category": "WHNP", "index": 0, "constituents": [{"category": "WDT", "index": 0, "constituents": [{"category": "that", "index": 0}]}]}, {"category": "S", "index": 1, "constituents": [{"category": "VP", "index": 0, "constituents": [{"category": "VBZ", "index": 0, "constituents": [{"category": "'s", "index": 0}]}, {"category": "SBAR", "index": 1, "constituents": [{"category": "S", "index": 0, "constituents": [{"category": "NP", "index": 0, "constituents": [{"category": "PRP", "index": 0, "constituents": [{"category": "we", "index": 0}]}]}, {"category": "VP", "index": 1, "constituents": [{"category": "VBD", "index": 0, "constituents": [{"category": "were", "index": 0}]}, {"category": "SBAR", "index": 1, "constituents": [{"category": "RB", "index": 0, "constituents": [{"category": "just", "index": 0}]}, {"category": "IN", "index": 1, "constituents": [{"category": "in", "index": 0}]}, {"category": "S", "index": 2, "constituents": [{"category": "NP", "index": 0, "constituents": [{"category": "EX", "index": 0, "constituents": [{"category": "there", "index": 0}]}]}, {"category": "NP-TMP", "index": 1, "constituents": [{"category": "NN", "index": 0, "constituents": [{"category": "yesterday", "index": 0}]}]}, {"category": "VP", "index": 2, "constituents": [{"category": "VBD", "index": 0, "constituents": [{"category": "went", "index": 0}]}, {"category": "PP", "index": 1, "constituents": [{"category": "IN", "index": 0, "constituents": [{"category": "around", "index": 0}]}, {"category": "NP", "index": 1, "constituents": [{"category": "PRP", "index": 0, "constituents": [{"category": "it", "index": 0}]}]}]}]}]}]}]}]}]}]}]}]}]}, {"category": "VP", "index": 1, "constituents": [{"category": "VBD", "index": 0, "constituents": [{"category": "was", "index": 0}]}, {"category": "NP", "index": 1, "constituents": [{"category": "PRP", "index": 0, "constituents": [{"category": "it", "index": 0}]}]}]}]}]}]}, {"category": "VP", "index": 1, "constituents": [{"category": "VBD", "index": 0, "constituents": [{"category": "was", "index": 0}]}, {"category": "NP", "index": 1, "constituents": [{"category": "PRP", "index": 0, "constituents": [{"category": "we", "index": 0}]}]}]}]}]}]}]}, {"category": "VP", "index": 1, "constituents": [{"category": "VBD", "index": 0, "constituents": [{"category": "went", "index": 0}]}, {"category": "ADVP", "index": 1, "constituents": [{"category": "RB", "index": 0, "constituents": [{"category": "up", "index": 0}]}]}, {"category": "SBAR", "index": 2, "constituents": [{"category": "IN", "index": 0, "constituents": [{"category": "in", "index": 0}]}, {"category": "S", "index": 1, "constituents": [{"category": "NP", "index": 0, "constituents": [{"category": "EX", "index": 0, "constituents": [{"category": "there", "index": 0}]}]}, {"category": "VP", "index": 1, "constituents": [{"category": "VBD", "index": 0, "constituents": [{"category": "was", "index": 0}]}, {"category": "S", "index": 1, "constituents": [{"category": "INTJ", "index": 0, "constituents": [{"category": "UH", "index": 0, "constituents": [{"category": "oh", "index": 0}]}]}, {"category": "VP", "index": 1, "constituents": [{"category": "VB", "index": 0, "constituents": [{"category": "forget", "index": 0}]}, {"category": "SBAR", "index": 1, "constituents": [{"category": "S", "index": 0, "constituents": [{"category": "NP", "index": 0, "constituents": [{"category": "PRP", "index": 0, "constituents": [{"category": "he", "index": 0}]}]}, {"category": "VP", "index": 1, "constituents": [{"category": "VBD", "index": 0, "constituents": [{"category": "was", "index": 0}]}, {"category": "PP", "index": 1, "constituents": [{"category": "IN", "index": 0, "constituents": [{"category": "in", "index": 0}]}, {"category": "SBAR", "index": 1, "constituents": [{"category": "WHNP", "index": 0, "constituents": [{"category": "DT", "index": 0, "constituents": [{"category": "that", "index": 0}]}]}, {"category": "S", "index": 1, "constituents": [{"category": "VP", "index": 0, "constituents": [{"category": "VBZ", "index": 0, "constituents": [{"category": "'s", "index": 0}]}, {"category": "NP", "index": 1, "constituents": [{"category": "NP", "index": 0, "constituents": [{"category": "DT", "index": 0, "constituents": [{"category": "the", "index": 0}]}, {"category": "NN", "index": 1, "constituents": [{"category": "name", "index": 0}]}]}, {"category": "NP", "index": 1, "constituents": [{"category": "DT", "index": 0, "constituents": [{"category": "this", "index": 0}]}, {"category": "CD", "index": 1, "constituents": [{"category": "one", "index": 0}]}]}]}]}, {"category": "NP", "index": 1, "constituents": [{"category": "EX", "index": 0, "constituents": [{"category": "there", "index": 0}]}]}]}]}]}]}]}]}]}]}]}]}]}]}]}]}}]}