{"coreferences": [{"mentions": [{"head": 8, "animacy": "INANIMATE", "end": 9, "sentence": 8, "text": "a tightrope walking", "number": "SINGULAR", "mention_type": "NOMINAL", "representativeness": 3, "start": 6, "coref_cluster_id": 16, "mention_id": 16, "gender": "UNKNOWN", "position": {"sent_num": 8, "mention_num": 2}, "is_representative": true}, {"head": 1, "animacy": "UNKNOWN", "end": 2, "sentence": 9, "text": "that", "number": "UNKNOWN", "mention_type": "PRONOMINAL", "representativeness": 1, "start": 1, "coref_cluster_id": 16, "mention_id": 17, "gender": "NEUTRAL", "position": {"sent_num": 9, "mention_num": 1}, "is_representative": false}, {"head": 3, "animacy": "INANIMATE", "end": 4, "sentence": 9, "text": "it", "number": "SINGULAR", "mention_type": "PRONOMINAL", "representativeness": 1, "start": 3, "coref_cluster_id": 16, "mention_id": 18, "gender": "NEUTRAL", "position": {"sent_num": 9, "mention_num": 2}, "is_representative": false}], "id": 16}, {"mentions": [{"head": 3, "animacy": "UNKNOWN", "end": 4, "sentence": 1, "text": "'s", "number": "UNKNOWN", "mention_type": "NOMINAL", "representativeness": 3, "start": 3, "coref_cluster_id": 1, "mention_id": 1, "gender": "UNKNOWN", "position": {"sent_num": 1, "mention_num": 1}, "is_representative": true}], "id": 1}, {"mentions": [{"head": 4, "animacy": "ANIMATE", "end": 5, "sentence": 2, "text": "a clown", "number": "SINGULAR", "mention_type": "NOMINAL", "representativeness": 3, "start": 3, "coref_cluster_id": 2, "mention_id": 2, "gender": "MALE", "position": {"sent_num": 2, "mention_num": 1}, "is_representative": true}, {"head": 6, "animacy": "ANIMATE", "end": 7, "sentence": 7, "text": "the clown", "number": "SINGULAR", "mention_type": "NOMINAL", "representativeness": 3, "start": 5, "coref_cluster_id": 2, "mention_id": 13, "gender": "MALE", "position": {"sent_num": 7, "mention_num": 2}, "is_representative": false}], "id": 2}, {"mentions": [{"head": 3, "animacy": "UNKNOWN", "end": 4, "sentence": 3, "text": "a", "number": "UNKNOWN", "mention_type": "NOMINAL", "representativeness": 3, "start": 3, "coref_cluster_id": 3, "mention_id": 3, "gender": "UNKNOWN", "position": {"sent_num": 3, "mention_num": 1}, "is_representative": true}, {"head": 12, "animacy": "INANIMATE", "end": 13, "sentence": 4, "text": "it", "number": "SINGULAR", "mention_type": "PRONOMINAL", "representativeness": 1, "start": 12, "coref_cluster_id": 3, "mention_id": 8, "gender": "NEUTRAL", "position": {"sent_num": 4, "mention_num": 4}, "is_representative": false}], "id": 3}, {"mentions": [{"head": 8, "animacy": "INANIMATE", "end": 9, "sentence": 3, "text": "a lion", "number": "SINGULAR", "mention_type": "NOMINAL", "representativeness": 3, "start": 7, "coref_cluster_id": 4, "mention_id": 4, "gender": "UNKNOWN", "position": {"sent_num": 3, "mention_num": 2}, "is_representative": true}, {"head": 9, "animacy": "INANIMATE", "end": 10, "sentence": 6, "text": "the lion", "number": "SINGULAR", "mention_type": "NOMINAL", "representativeness": 3, "start": 8, "coref_cluster_id": 4, "mention_id": 11, "gender": "UNKNOWN", "position": {"sent_num": 6, "mention_num": 2}, "is_representative": false}, {"head": 2, "animacy": "INANIMATE", "end": 3, "sentence": 7, "text": "it", "number": "SINGULAR", "mention_type": "PRONOMINAL", "representativeness": 1, "start": 2, "coref_cluster_id": 4, "mention_id": 12, "gender": "NEUTRAL", "position": {"sent_num": 7, "mention_num": 1}, "is_representative": false}], "id": 4}, {"mentions": [{"head": 2, "animacy": "INANIMATE", "end": 14, "sentence": 4, "text": "a horse walkin ' around with a woman on top of it .", "number": "SINGULAR", "mention_type": "NOMINAL", "representativeness": 3, "start": 1, "coref_cluster_id": 5, "mention_id": 5, "gender": "MALE", "position": {"sent_num": 4, "mention_num": 1}, "is_representative": true}], "id": 5}, {"mentions": [{"head": 8, "animacy": "ANIMATE", "end": 13, "sentence": 4, "text": "a woman on top of it", "number": "SINGULAR", "mention_type": "NOMINAL", "representativeness": 3, "start": 7, "coref_cluster_id": 6, "mention_id": 6, "gender": "FEMALE", "position": {"sent_num": 4, "mention_num": 2}, "is_representative": true}], "id": 6}, {"mentions": [{"head": 10, "animacy": "INANIMATE", "end": 13, "sentence": 4, "text": "top of it", "number": "SINGULAR", "mention_type": "NOMINAL", "representativeness": 3, "start": 10, "coref_cluster_id": 7, "mention_id": 7, "gender": "UNKNOWN", "position": {"sent_num": 4, "mention_num": 3}, "is_representative": true}], "id": 7}, {"mentions": [{"head": 3, "animacy": "ANIMATE", "end": 4, "sentence": 5, "text": "children", "number": "PLURAL", "mention_type": "NOMINAL", "representativeness": 3, "start": 3, "coref_cluster_id": 9, "mention_id": 9, "gender": "UNKNOWN", "position": {"sent_num": 5, "mention_num": 1}, "is_representative": true}], "id": 9}, {"mentions": [{"head": 4, "animacy": "ANIMATE", "end": 10, "sentence": 6, "text": "a trainer in there with the lion", "number": "SINGULAR", "mention_type": "NOMINAL", "representativeness": 3, "start": 3, "coref_cluster_id": 10, "mention_id": 10, "gender": "MALE", "position": {"sent_num": 6, "mention_num": 1}, "is_representative": true}], "id": 10}, {"mentions": [{"head": 15, "animacy": "ANIMATE", "end": 16, "sentence": 7, "text": "the kids", "number": "PLURAL", "mention_type": "NOMINAL", "representativeness": 3, "start": 14, "coref_cluster_id": 14, "mention_id": 14, "gender": "UNKNOWN", "position": {"sent_num": 7, "mention_num": 3}, "is_representative": true}], "id": 14}, {"mentions": [{"head": 4, "animacy": "ANIMATE", "end": 9, "sentence": 8, "text": "somebody on a tightrope walking", "number": "SINGULAR", "mention_type": "NOMINAL", "representativeness": 3, "start": 4, "coref_cluster_id": 15, "mention_id": 15, "gender": "UNKNOWN", "position": {"sent_num": 8, "mention_num": 1}, "is_representative": true}], "id": 15}], "sentences": [{"tokens": [{"index": 0, "word": "well", "character_offset_begin": 0, "character_offset_end": 4, "pos": "RB", "lemma": "well", "speaker": "PER0", "ner": "O"}, {"index": 1, "word": "let", "character_offset_begin": 5, "character_offset_end": 8, "pos": "VB", "lemma": "let", "speaker": "PER0", "ner": "O"}, {"index": 2, "word": "'s", "character_offset_begin": 8, "character_offset_end": 10, "pos": "POS", "lemma": "'s", "speaker": "PER0", "ner": "O"}, {"index": 3, "word": "see", "character_offset_begin": 11, "character_offset_end": 14, "pos": "VB", "lemma": "see", "speaker": "PER0", "ner": "O"}, {"index": 4, "word": ".", "character_offset_begin": 14, "character_offset_end": 15, "pos": ".", "lemma": ".", "speaker": "PER0", "ner": "O"}], "index": 0, "dependencies": [{"target": {"index": 1, "begin_position": 0, "value": "well", "end_position": 4}, "dependent": {"index": 1, "begin_position": 0, "value": "well", "end_position": 4}, "is_extra": false, "governor": {"index": 2, "begin_position": 5, "value": "let", "end_position": 8}, "source": {"index": 2, "begin_position": 5, "value": "let", "end_position": 8}, "relation": {"description": "discourse element", "value": "discourse"}}, {"target": {"index": 4, "begin_position": 11, "value": "see", "end_position": 14}, "dependent": {"index": 4, "begin_position": 11, "value": "see", "end_position": 14}, "is_extra": false, "governor": {"index": 2, "begin_position": 5, "value": "let", "end_position": 8}, "source": {"index": 2, "begin_position": 5, "value": "let", "end_position": 8}, "relation": {"description": "clausal complement", "value": "ccomp"}}, {"target": {"index": 3, "begin_position": 8, "value": "'s", "end_position": 10}, "dependent": {"index": 3, "begin_position": 8, "value": "'s", "end_position": 10}, "is_extra": false, "governor": {"index": 4, "begin_position": 11, "value": "see", "end_position": 14}, "source": {"index": 4, "begin_position": 11, "value": "see", "end_position": 14}, "relation": {"description": "nominal subject", "value": "nsubj"}}], "phrase_structure": {"category": "ROOT", "constituents": [{"category": "S", "index": 0, "constituents": [{"category": "INTJ", "index": 0, "constituents": [{"category": "RB", "index": 0, "constituents": [{"category": "well", "index": 0}]}]}, {"category": "VP", "index": 1, "constituents": [{"category": "VB", "index": 0, "constituents": [{"category": "let", "index": 0}]}, {"category": "S", "index": 1, "constituents": [{"category": "NP", "index": 0, "constituents": [{"category": "POS", "index": 0, "constituents": [{"category": "'s", "index": 0}]}]}, {"category": "VP", "index": 1, "constituents": [{"category": "VB", "index": 0, "constituents": [{"category": "see", "index": 0}]}]}]}]}, {"category": ".", "index": 2, "constituents": [{"category": ".", "index": 0}]}]}]}}, {"tokens": [{"index": 0, "word": "i", "character_offset_begin": 16, "character_offset_end": 17, "pos": "LS", "lemma": "i", "speaker": "PER0", "ner": "O"}, {"index": 1, "word": "see", "character_offset_begin": 18, "character_offset_end": 21, "pos": "VB", "lemma": "see", "speaker": "PER0", "ner": "O"}, {"index": 2, "word": "a", "character_offset_begin": 22, "character_offset_end": 23, "pos": "DT", "lemma": "a", "speaker": "PER0", "ner": "O"}, {"index": 3, "word": "clown", "character_offset_begin": 24, "character_offset_end": 29, "pos": "NN", "lemma": "clown", "speaker": "PER0", "ner": "O"}, {"index": 4, "word": ".", "character_offset_begin": 29, "character_offset_end": 30, "pos": ".", "lemma": ".", "speaker": "PER0", "ner": "O"}], "index": 1, "dependencies": [{"target": {"index": 3, "begin_position": 22, "value": "a", "end_position": 23}, "dependent": {"index": 3, "begin_position": 22, "value": "a", "end_position": 23}, "is_extra": false, "governor": {"index": 4, "begin_position": 24, "value": "clown", "end_position": 29}, "source": {"index": 4, "begin_position": 24, "value": "clown", "end_position": 29}, "relation": {"description": "determiner", "value": "det"}}, {"target": {"index": 4, "begin_position": 24, "value": "clown", "end_position": 29}, "dependent": {"index": 4, "begin_position": 24, "value": "clown", "end_position": 29}, "is_extra": false, "governor": {"index": 2, "begin_position": 18, "value": "see", "end_position": 21}, "source": {"index": 2, "begin_position": 18, "value": "see", "end_position": 21}, "relation": {"description": "direct object", "value": "dobj"}}, {"target": {"index": 1, "begin_position": 16, "value": "i", "end_position": 17}, "dependent": {"index": 1, "begin_position": 16, "value": "i", "end_position": 17}, "is_extra": false, "governor": {"index": 2, "begin_position": 18, "value": "see", "end_position": 21}, "source": {"index": 2, "begin_position": 18, "value": "see", "end_position": 21}, "relation": {"description": "dependent", "value": "dep"}}], "phrase_structure": {"category": "ROOT", "constituents": [{"category": "S", "index": 0, "constituents": [{"category": "LS", "index": 0, "constituents": [{"category": "i", "index": 0}]}, {"category": "VP", "index": 1, "constituents": [{"category": "VB", "index": 0, "constituents": [{"category": "see", "index": 0}]}, {"category": "NP", "index": 1, "constituents": [{"category": "DT", "index": 0, "constituents": [{"category": "a", "index": 0}]}, {"category": "NN", "index": 1, "constituents": [{"category": "clown", "index": 0}]}]}]}, {"category": ".", "index": 2, "constituents": [{"category": ".", "index": 0}]}]}]}}, {"tokens": [{"index": 0, "word": "i", "character_offset_begin": 31, "character_offset_end": 32, "pos": "LS", "lemma": "i", "speaker": "PER0", "ner": "O"}, {"index": 1, "word": "see", "character_offset_begin": 33, "character_offset_end": 36, "pos": "VB", "lemma": "see", "speaker": "PER0", "ner": "O"}, {"index": 2, "word": "a", "character_offset_begin": 37, "character_offset_end": 38, "pos": "DT", "lemma": "a", "speaker": "PER0", "ner": "O"}, {"index": 3, "word": ",", "character_offset_begin": 38, "character_offset_end": 39, "pos": ",", "lemma": ",", "speaker": "PER0", "ner": "O"}, {"index": 4, "word": "looks", "character_offset_begin": 40, "character_offset_end": 45, "pos": "VBZ", "lemma": "look", "speaker": "PER0", "ner": "O"}, {"index": 5, "word": "like", "character_offset_begin": 46, "character_offset_end": 50, "pos": "IN", "lemma": "like", "speaker": "PER0", "ner": "O"}, {"index": 6, "word": "a", "character_offset_begin": 51, "character_offset_end": 52, "pos": "DT", "lemma": "a", "speaker": "PER0", "ner": "O"}, {"index": 7, "word": "lion", "character_offset_begin": 53, "character_offset_end": 57, "pos": "NN", "lemma": "lion", "speaker": "PER0", "ner": "O"}, {"index": 8, "word": ".", "character_offset_begin": 57, "character_offset_end": 58, "pos": ".", "lemma": ".", "speaker": "PER0", "ner": "O"}], "index": 2, "dependencies": [{"target": {"index": 7, "begin_position": 51, "value": "a", "end_position": 52}, "dependent": {"index": 7, "begin_position": 51, "value": "a", "end_position": 52}, "is_extra": false, "governor": {"index": 8, "begin_position": 53, "value": "lion", "end_position": 57}, "source": {"index": 8, "begin_position": 53, "value": "lion", "end_position": 57}, "relation": {"description": "determiner", "value": "det"}}, {"target": {"index": 3, "begin_position": 37, "value": "a", "end_position": 38}, "dependent": {"index": 3, "begin_position": 37, "value": "a", "end_position": 38}, "is_extra": false, "governor": {"index": 2, "begin_position": 33, "value": "see", "end_position": 36}, "source": {"index": 2, "begin_position": 33, "value": "see", "end_position": 36}, "relation": {"description": "direct object", "value": "dobj"}}, {"target": {"index": 8, "begin_position": 53, "value": "lion", "end_position": 57}, "dependent": {"index": 8, "begin_position": 53, "value": "lion", "end_position": 57}, "is_extra": false, "governor": {"index": 5, "begin_position": 40, "value": "looks", "end_position": 45}, "source": {"index": 5, "begin_position": 40, "value": "looks", "end_position": 45}, "relation": {"description": "prep_collapsed", "value": "prep"}}, {"target": {"index": 1, "begin_position": 31, "value": "i", "end_position": 32}, "dependent": {"index": 1, "begin_position": 31, "value": "i", "end_position": 32}, "is_extra": false, "governor": {"index": 5, "begin_position": 40, "value": "looks", "end_position": 45}, "source": {"index": 5, "begin_position": 40, "value": "looks", "end_position": 45}, "relation": {"description": "dependent", "value": "dep"}}, {"target": {"index": 2, "begin_position": 33, "value": "see", "end_position": 36}, "dependent": {"index": 2, "begin_position": 33, "value": "see", "end_position": 36}, "is_extra": false, "governor": {"index": 5, "begin_position": 40, "value": "looks", "end_position": 45}, "source": {"index": 5, "begin_position": 40, "value": "looks", "end_position": 45}, "relation": {"description": "clausal complement", "value": "ccomp"}}], "phrase_structure": {"category": "ROOT", "constituents": [{"category": "S", "index": 0, "constituents": [{"category": "LS", "index": 0, "constituents": [{"category": "i", "index": 0}]}, {"category": "S", "index": 1, "constituents": [{"category": "VP", "index": 0, "constituents": [{"category": "VB", "index": 0, "constituents": [{"category": "see", "index": 0}]}, {"category": "NP", "index": 1, "constituents": [{"category": "DT", "index": 0, "constituents": [{"category": "a", "index": 0}]}]}]}]}, {"category": ",", "index": 2, "constituents": [{"category": ",", "index": 0}]}, {"category": "VP", "index": 3, "constituents": [{"category": "VBZ", "index": 0, "constituents": [{"category": "looks", "index": 0}]}, {"category": "PP", "index": 1, "constituents": [{"category": "IN", "index": 0, "constituents": [{"category": "like", "index": 0}]}, {"category": "NP", "index": 1, "constituents": [{"category": "DT", "index": 0, "constituents": [{"category": "a", "index": 0}]}, {"category": "NN", "index": 1, "constituents": [{"category": "lion", "index": 0}]}]}]}]}, {"category": ".", "index": 4, "constituents": [{"category": ".", "index": 0}]}]}]}}, {"tokens": [{"index": 0, "word": "a", "character_offset_begin": 59, "character_offset_end": 60, "pos": "DT", "lemma": "a", "speaker": "PER0", "ner": "O"}, {"index": 1, "word": "horse", "character_offset_begin": 61, "character_offset_end": 66, "pos": "NN", "lemma": "horse", "speaker": "PER0", "ner": "O"}, {"index": 2, "word": "walkin", "character_offset_begin": 67, "character_offset_end": 73, "pos": "VBG", "lemma": "walkin", "speaker": "PER0", "ner": "O"}, {"index": 3, "word": "'", "character_offset_begin": 73, "character_offset_end": 74, "pos": "''", "lemma": "'", "speaker": "PER0", "ner": "O"}, {"index": 4, "word": "around", "character_offset_begin": 75, "character_offset_end": 81, "pos": "IN", "lemma": "around", "speaker": "PER0", "ner": "O"}, {"index": 5, "word": "with", "character_offset_begin": 82, "character_offset_end": 86, "pos": "IN", "lemma": "with", "speaker": "PER0", "ner": "O"}, {"index": 6, "word": "a", "character_offset_begin": 87, "character_offset_end": 88, "pos": "DT", "lemma": "a", "speaker": "PER0", "ner": "O"}, {"index": 7, "word": "woman", "character_offset_begin": 89, "character_offset_end": 94, "pos": "NN", "lemma": "woman", "speaker": "PER0", "ner": "O"}, {"index": 8, "word": "on", "character_offset_begin": 95, "character_offset_end": 97, "pos": "IN", "lemma": "on", "speaker": "PER0", "ner": "O"}, {"index": 9, "word": "top", "character_offset_begin": 98, "character_offset_end": 101, "pos": "NN", "lemma": "top", "speaker": "PER0", "ner": "O"}, {"index": 10, "word": "of", "character_offset_begin": 102, "character_offset_end": 104, "pos": "IN", "lemma": "of", "speaker": "PER0", "ner": "O"}, {"index": 11, "word": "it", "character_offset_begin": 105, "character_offset_end": 107, "pos": "PRP", "lemma": "it", "speaker": "PER0", "ner": "O"}, {"index": 12, "word": ".", "character_offset_begin": 107, "character_offset_end": 108, "pos": ".", "lemma": ".", "speaker": "PER0", "ner": "O"}], "index": 3, "dependencies": [{"target": {"index": 1, "begin_position": 59, "value": "a", "end_position": 60}, "dependent": {"index": 1, "begin_position": 59, "value": "a", "end_position": 60}, "is_extra": false, "governor": {"index": 2, "begin_position": 61, "value": "horse", "end_position": 66}, "source": {"index": 2, "begin_position": 61, "value": "horse", "end_position": 66}, "relation": {"description": "determiner", "value": "det"}}, {"target": {"index": 3, "begin_position": 67, "value": "walkin", "end_position": 73}, "dependent": {"index": 3, "begin_position": 67, "value": "walkin", "end_position": 73}, "is_extra": false, "governor": {"index": 2, "begin_position": 61, "value": "horse", "end_position": 66}, "source": {"index": 2, "begin_position": 61, "value": "horse", "end_position": 66}, "relation": {"description": "verb modifier", "value": "vmod"}}, {"target": {"index": 5, "begin_position": 75, "value": "around", "end_position": 81}, "dependent": {"index": 5, "begin_position": 75, "value": "around", "end_position": 81}, "is_extra": false, "governor": {"index": 3, "begin_position": 67, "value": "walkin", "end_position": 73}, "source": {"index": 3, "begin_position": 67, "value": "walkin", "end_position": 73}, "relation": {"description": "dependent", "value": "dep"}}, {"target": {"index": 8, "begin_position": 89, "value": "woman", "end_position": 94}, "dependent": {"index": 8, "begin_position": 89, "value": "woman", "end_position": 94}, "is_extra": false, "governor": {"index": 3, "begin_position": 67, "value": "walkin", "end_position": 73}, "source": {"index": 3, "begin_position": 67, "value": "walkin", "end_position": 73}, "relation": {"description": "prep_collapsed", "value": "prep"}}, {"target": {"index": 12, "begin_position": 105, "value": "it", "end_position": 107}, "dependent": {"index": 12, "begin_position": 105, "value": "it", "end_position": 107}, "is_extra": false, "governor": {"index": 8, "begin_position": 89, "value": "woman", "end_position": 94}, "source": {"index": 8, "begin_position": 89, "value": "woman", "end_position": 94}, "relation": {"description": "prep_collapsed", "value": "prep"}}, {"target": {"index": 7, "begin_position": 87, "value": "a", "end_position": 88}, "dependent": {"index": 7, "begin_position": 87, "value": "a", "end_position": 88}, "is_extra": false, "governor": {"index": 8, "begin_position": 89, "value": "woman", "end_position": 94}, "source": {"index": 8, "begin_position": 89, "value": "woman", "end_position": 94}, "relation": {"description": "determiner", "value": "det"}}], "phrase_structure": {"category": "ROOT", "constituents": [{"category": "NP", "index": 0, "constituents": [{"category": "NP", "index": 0, "constituents": [{"category": "DT", "index": 0, "constituents": [{"category": "a", "index": 0}]}, {"category": "NN", "index": 1, "constituents": [{"category": "horse", "index": 0}]}]}, {"category": "VP", "index": 1, "constituents": [{"category": "VBG", "index": 0, "constituents": [{"category": "walkin", "index": 0}]}, {"category": "''", "index": 1, "constituents": [{"category": "'", "index": 0}]}, {"category": "PP", "index": 2, "constituents": [{"category": "IN", "index": 0, "constituents": [{"category": "around", "index": 0}]}, {"category": "IN", "index": 1, "constituents": [{"category": "with", "index": 0}]}, {"category": "NP", "index": 2, "constituents": [{"category": "NP", "index": 0, "constituents": [{"category": "DT", "index": 0, "constituents": [{"category": "a", "index": 0}]}, {"category": "NN", "index": 1, "constituents": [{"category": "woman", "index": 0}]}]}, {"category": "PP", "index": 1, "constituents": [{"category": "IN", "index": 0, "constituents": [{"category": "on", "index": 0}]}, {"category": "NP", "index": 1, "constituents": [{"category": "NP", "index": 0, "constituents": [{"category": "NN", "index": 0, "constituents": [{"category": "top", "index": 0}]}]}, {"category": "PP", "index": 1, "constituents": [{"category": "IN", "index": 0, "constituents": [{"category": "of", "index": 0}]}, {"category": "NP", "index": 1, "constituents": [{"category": "PRP", "index": 0, "constituents": [{"category": "it", "index": 0}]}]}]}]}]}]}]}]}, {"category": ".", "index": 2, "constituents": [{"category": ".", "index": 0}]}]}]}}, {"tokens": [{"index": 0, "word": "there", "character_offset_begin": 109, "character_offset_end": 114, "pos": "EX", "lemma": "there", "speaker": "PER0", "ner": "O"}, {"index": 1, "word": "'s", "character_offset_begin": 114, "character_offset_end": 116, "pos": "VBZ", "lemma": "be", "speaker": "PER0", "ner": "O"}, {"index": 2, "word": "children", "character_offset_begin": 117, "character_offset_end": 125, "pos": "NNS", "lemma": "child", "speaker": "PER0", "ner": "O"}, {"index": 3, "word": ".", "character_offset_begin": 125, "character_offset_end": 126, "pos": ".", "lemma": ".", "speaker": "PER0", "ner": "O"}], "index": 4, "dependencies": [{"target": {"index": 1, "begin_position": 109, "value": "there", "end_position": 114}, "dependent": {"index": 1, "begin_position": 109, "value": "there", "end_position": 114}, "is_extra": false, "governor": {"index": 2, "begin_position": 114, "value": "'s", "end_position": 116}, "source": {"index": 2, "begin_position": 114, "value": "'s", "end_position": 116}, "relation": {"description": "expletive", "value": "expl"}}, {"target": {"index": 3, "begin_position": 117, "value": "children", "end_position": 125}, "dependent": {"index": 3, "begin_position": 117, "value": "children", "end_position": 125}, "is_extra": false, "governor": {"index": 2, "begin_position": 114, "value": "'s", "end_position": 116}, "source": {"index": 2, "begin_position": 114, "value": "'s", "end_position": 116}, "relation": {"description": "nominal subject", "value": "nsubj"}}], "phrase_structure": {"category": "ROOT", "constituents": [{"category": "S", "index": 0, "constituents": [{"category": "NP", "index": 0, "constituents": [{"category": "EX", "index": 0, "constituents": [{"category": "there", "index": 0}]}]}, {"category": "VP", "index": 1, "constituents": [{"category": "VBZ", "index": 0, "constituents": [{"category": "'s", "index": 0}]}, {"category": "NP", "index": 1, "constituents": [{"category": "NNS", "index": 0, "constituents": [{"category": "children", "index": 0}]}]}]}, {"category": ".", "index": 2, "constituents": [{"category": ".", "index": 0}]}]}]}}, {"tokens": [{"index": 0, "word": "there", "character_offset_begin": 127, "character_offset_end": 132, "pos": "EX", "lemma": "there", "speaker": "PER0", "ner": "O"}, {"index": 1, "word": "'s", "character_offset_begin": 132, "character_offset_end": 134, "pos": "VBZ", "lemma": "be", "speaker": "PER0", "ner": "O"}, {"index": 2, "word": "a", "character_offset_begin": 135, "character_offset_end": 136, "pos": "DT", "lemma": "a", "speaker": "PER0", "ner": "O"}, {"index": 3, "word": "trainer", "character_offset_begin": 137, "character_offset_end": 144, "pos": "NN", "lemma": "trainer", "speaker": "PER0", "ner": "O"}, {"index": 4, "word": "in", "character_offset_begin": 145, "character_offset_end": 147, "pos": "IN", "lemma": "in", "speaker": "PER0", "ner": "O"}, {"index": 5, "word": "there", "character_offset_begin": 148, "character_offset_end": 153, "pos": "EX", "lemma": "there", "speaker": "PER0", "ner": "O"}, {"index": 6, "word": "with", "character_offset_begin": 154, "character_offset_end": 158, "pos": "IN", "lemma": "with", "speaker": "PER0", "ner": "O"}, {"index": 7, "word": "the", "character_offset_begin": 159, "character_offset_end": 162, "pos": "DT", "lemma": "the", "speaker": "PER0", "ner": "O"}, {"index": 8, "word": "lion", "character_offset_begin": 163, "character_offset_end": 167, "pos": "NN", "lemma": "lion", "speaker": "PER0", "ner": "O"}, {"index": 9, "word": ".", "character_offset_begin": 167, "character_offset_end": 168, "pos": ".", "lemma": ".", "speaker": "PER0", "ner": "O"}], "index": 5, "dependencies": [{"target": {"index": 1, "begin_position": 127, "value": "there", "end_position": 132}, "dependent": {"index": 1, "begin_position": 127, "value": "there", "end_position": 132}, "is_extra": false, "governor": {"index": 2, "begin_position": 132, "value": "'s", "end_position": 134}, "source": {"index": 2, "begin_position": 132, "value": "'s", "end_position": 134}, "relation": {"description": "expletive", "value": "expl"}}, {"target": {"index": 4, "begin_position": 137, "value": "trainer", "end_position": 144}, "dependent": {"index": 4, "begin_position": 137, "value": "trainer", "end_position": 144}, "is_extra": false, "governor": {"index": 2, "begin_position": 132, "value": "'s", "end_position": 134}, "source": {"index": 2, "begin_position": 132, "value": "'s", "end_position": 134}, "relation": {"description": "nominal subject", "value": "nsubj"}}, {"target": {"index": 3, "begin_position": 135, "value": "a", "end_position": 136}, "dependent": {"index": 3, "begin_position": 135, "value": "a", "end_position": 136}, "is_extra": false, "governor": {"index": 4, "begin_position": 137, "value": "trainer", "end_position": 144}, "source": {"index": 4, "begin_position": 137, "value": "trainer", "end_position": 144}, "relation": {"description": "determiner", "value": "det"}}, {"target": {"index": 6, "begin_position": 148, "value": "there", "end_position": 153}, "dependent": {"index": 6, "begin_position": 148, "value": "there", "end_position": 153}, "is_extra": false, "governor": {"index": 4, "begin_position": 137, "value": "trainer", "end_position": 144}, "source": {"index": 4, "begin_position": 137, "value": "trainer", "end_position": 144}, "relation": {"description": "prep_collapsed", "value": "prep"}}, {"target": {"index": 9, "begin_position": 163, "value": "lion", "end_position": 167}, "dependent": {"index": 9, "begin_position": 163, "value": "lion", "end_position": 167}, "is_extra": false, "governor": {"index": 4, "begin_position": 137, "value": "trainer", "end_position": 144}, "source": {"index": 4, "begin_position": 137, "value": "trainer", "end_position": 144}, "relation": {"description": "prep_collapsed", "value": "prep"}}, {"target": {"index": 8, "begin_position": 159, "value": "the", "end_position": 162}, "dependent": {"index": 8, "begin_position": 159, "value": "the", "end_position": 162}, "is_extra": false, "governor": {"index": 9, "begin_position": 163, "value": "lion", "end_position": 167}, "source": {"index": 9, "begin_position": 163, "value": "lion", "end_position": 167}, "relation": {"description": "determiner", "value": "det"}}], "phrase_structure": {"category": "ROOT", "constituents": [{"category": "S", "index": 0, "constituents": [{"category": "NP", "index": 0, "constituents": [{"category": "EX", "index": 0, "constituents": [{"category": "there", "index": 0}]}]}, {"category": "VP", "index": 1, "constituents": [{"category": "VBZ", "index": 0, "constituents": [{"category": "'s", "index": 0}]}, {"category": "NP", "index": 1, "constituents": [{"category": "NP", "index": 0, "constituents": [{"category": "DT", "index": 0, "constituents": [{"category": "a", "index": 0}]}, {"category": "NN", "index": 1, "constituents": [{"category": "trainer", "index": 0}]}]}, {"category": "PP", "index": 1, "constituents": [{"category": "IN", "index": 0, "constituents": [{"category": "in", "index": 0}]}, {"category": "NP", "index": 1, "constituents": [{"category": "EX", "index": 0, "constituents": [{"category": "there", "index": 0}]}]}]}, {"category": "PP", "index": 2, "constituents": [{"category": "IN", "index": 0, "constituents": [{"category": "with", "index": 0}]}, {"category": "NP", "index": 1, "constituents": [{"category": "DT", "index": 0, "constituents": [{"category": "the", "index": 0}]}, {"category": "NN", "index": 1, "constituents": [{"category": "lion", "index": 0}]}]}]}]}]}, {"category": ".", "index": 2, "constituents": [{"category": ".", "index": 0}]}]}]}}, {"tokens": [{"index": 0, "word": "and", "character_offset_begin": 169, "character_offset_end": 172, "pos": "CC", "lemma": "and", "speaker": "PER0", "ner": "O"}, {"index": 1, "word": "it", "character_offset_begin": 173, "character_offset_end": 175, "pos": "PRP", "lemma": "it", "speaker": "PER0", "ner": "O"}, {"index": 2, "word": "looks", "character_offset_begin": 176, "character_offset_end": 181, "pos": "VBZ", "lemma": "look", "speaker": "PER0", "ner": "O"}, {"index": 3, "word": "like", "character_offset_begin": 182, "character_offset_end": 186, "pos": "IN", "lemma": "like", "speaker": "PER0", "ner": "O"}, {"index": 4, "word": "the", "character_offset_begin": 187, "character_offset_end": 190, "pos": "DT", "lemma": "the", "speaker": "PER0", "ner": "O"}, {"index": 5, "word": "clown", "character_offset_begin": 191, "character_offset_end": 196, "pos": "NN", "lemma": "clown", "speaker": "PER0", "ner": "O"}, {"index": 6, "word": "is", "character_offset_begin": 197, "character_offset_end": 199, "pos": "VBZ", "lemma": "be", "speaker": "PER0", "ner": "O"}, {"index": 7, "word": "maybe", "character_offset_begin": 200, "character_offset_end": 205, "pos": "RB", "lemma": "maybe", "speaker": "PER0", "ner": "O"}, {"index": 8, "word": "throwin", "character_offset_begin": 206, "character_offset_end": 213, "pos": "VBG", "lemma": "throwin", "speaker": "PER0", "ner": "O"}, {"index": 9, "word": "'", "character_offset_begin": 213, "character_offset_end": 214, "pos": "''", "lemma": "'", "speaker": "PER0", "ner": "O"}, {"index": 10, "word": ",", "character_offset_begin": 214, "character_offset_end": 215, "pos": ",", "lemma": ",", "speaker": "PER0", "ner": "O"}, {"index": 11, "word": "popcorn", "character_offset_begin": 216, "character_offset_end": 223, "pos": "NN", "lemma": "popcorn", "speaker": "PER0", "ner": "O"}, {"index": 12, "word": "to", "character_offset_begin": 224, "character_offset_end": 226, "pos": "TO", "lemma": "to", "speaker": "PER0", "ner": "O"}, {"index": 13, "word": "the", "character_offset_begin": 227, "character_offset_end": 230, "pos": "DT", "lemma": "the", "speaker": "PER0", "ner": "O"}, {"index": 14, "word": "kids", "character_offset_begin": 231, "character_offset_end": 235, "pos": "NNS", "lemma": "kid", "speaker": "PER0", "ner": "O"}, {"index": 15, "word": ".", "character_offset_begin": 235, "character_offset_end": 236, "pos": ".", "lemma": ".", "speaker": "PER0", "ner": "O"}], "index": 6, "dependencies": [{"target": {"index": 2, "begin_position": 173, "value": "it", "end_position": 175}, "dependent": {"index": 2, "begin_position": 173, "value": "it", "end_position": 175}, "is_extra": false, "governor": {"index": 3, "begin_position": 176, "value": "looks", "end_position": 181}, "source": {"index": 3, "begin_position": 176, "value": "looks", "end_position": 181}, "relation": {"description": "nominal subject", "value": "nsubj"}}, {"target": {"index": 9, "begin_position": 206, "value": "throwin", "end_position": 213}, "dependent": {"index": 9, "begin_position": 206, "value": "throwin", "end_position": 213}, "is_extra": false, "governor": {"index": 3, "begin_position": 176, "value": "looks", "end_position": 181}, "source": {"index": 3, "begin_position": 176, "value": "looks", "end_position": 181}, "relation": {"description": "adverbial clause modifier", "value": "advcl"}}, {"target": {"index": 12, "begin_position": 216, "value": "popcorn", "end_position": 223}, "dependent": {"index": 12, "begin_position": 216, "value": "popcorn", "end_position": 223}, "is_extra": false, "governor": {"index": 3, "begin_position": 176, "value": "looks", "end_position": 181}, "source": {"index": 3, "begin_position": 176, "value": "looks", "end_position": 181}, "relation": {"description": "parataxis", "value": "parataxis"}}, {"target": {"index": 1, "begin_position": 169, "value": "and", "end_position": 172}, "dependent": {"index": 1, "begin_position": 169, "value": "and", "end_position": 172}, "is_extra": false, "governor": {"index": 3, "begin_position": 176, "value": "looks", "end_position": 181}, "source": {"index": 3, "begin_position": 176, "value": "looks", "end_position": 181}, "relation": {"description": "coordination", "value": "cc"}}, {"target": {"index": 5, "begin_position": 187, "value": "the", "end_position": 190}, "dependent": {"index": 5, "begin_position": 187, "value": "the", "end_position": 190}, "is_extra": false, "governor": {"index": 6, "begin_position": 191, "value": "clown", "end_position": 196}, "source": {"index": 6, "begin_position": 191, "value": "clown", "end_position": 196}, "relation": {"description": "determiner", "value": "det"}}, {"target": {"index": 4, "begin_position": 182, "value": "like", "end_position": 186}, "dependent": {"index": 4, "begin_position": 182, "value": "like", "end_position": 186}, "is_extra": false, "governor": {"index": 9, "begin_position": 206, "value": "throwin", "end_position": 213}, "source": {"index": 9, "begin_position": 206, "value": "throwin", "end_position": 213}, "relation": {"description": "marker", "value": "mark"}}, {"target": {"index": 6, "begin_position": 191, "value": "clown", "end_position": 196}, "dependent": {"index": 6, "begin_position": 191, "value": "clown", "end_position": 196}, "is_extra": false, "governor": {"index": 9, "begin_position": 206, "value": "throwin", "end_position": 213}, "source": {"index": 9, "begin_position": 206, "value": "throwin", "end_position": 213}, "relation": {"description": "nominal subject", "value": "nsubj"}}, {"target": {"index": 7, "begin_position": 197, "value": "is", "end_position": 199}, "dependent": {"index": 7, "begin_position": 197, "value": "is", "end_position": 199}, "is_extra": false, "governor": {"index": 9, "begin_position": 206, "value": "throwin", "end_position": 213}, "source": {"index": 9, "begin_position": 206, "value": "throwin", "end_position": 213}, "relation": {"description": "auxiliary", "value": "aux"}}, {"target": {"index": 8, "begin_position": 200, "value": "maybe", "end_position": 205}, "dependent": {"index": 8, "begin_position": 200, "value": "maybe", "end_position": 205}, "is_extra": false, "governor": {"index": 9, "begin_position": 206, "value": "throwin", "end_position": 213}, "source": {"index": 9, "begin_position": 206, "value": "throwin", "end_position": 213}, "relation": {"description": "adverbial modifier", "value": "advmod"}}, {"target": {"index": 13, "begin_position": 224, "value": "to", "end_position": 226}, "dependent": {"index": 13, "begin_position": 224, "value": "to", "end_position": 226}, "is_extra": false, "governor": {"index": 12, "begin_position": 216, "value": "popcorn", "end_position": 223}, "source": {"index": 12, "begin_position": 216, "value": "popcorn", "end_position": 223}, "relation": {"description": "dependent", "value": "dep"}}, {"target": {"index": 15, "begin_position": 231, "value": "kids", "end_position": 235}, "dependent": {"index": 15, "begin_position": 231, "value": "kids", "end_position": 235}, "is_extra": false, "governor": {"index": 13, "begin_position": 224, "value": "to", "end_position": 226}, "source": {"index": 13, "begin_position": 224, "value": "to", "end_position": 226}, "relation": {"description": "prepositional object", "value": "pobj"}}, {"target": {"index": 14, "begin_position": 227, "value": "the", "end_position": 230}, "dependent": {"index": 14, "begin_position": 227, "value": "the", "end_position": 230}, "is_extra": false, "governor": {"index": 15, "begin_position": 231, "value": "kids", "end_position": 235}, "source": {"index": 15, "begin_position": 231, "value": "kids", "end_position": 235}, "relation": {"description": "determiner", "value": "det"}}], "phrase_structure": {"category": "ROOT", "constituents": [{"category": "S", "index": 0, "constituents": [{"category": "S", "index": 0, "constituents": [{"category": "CC", "index": 0, "constituents": [{"category": "and", "index": 0}]}, {"category": "NP", "index": 1, "constituents": [{"category": "PRP", "index": 0, "constituents": [{"category": "it", "index": 0}]}]}, {"category": "VP", "index": 2, "constituents": [{"category": "VBZ", "index": 0, "constituents": [{"category": "looks", "index": 0}]}, {"category": "SBAR", "index": 1, "constituents": [{"category": "IN", "index": 0, "constituents": [{"category": "like", "index": 0}]}, {"category": "S", "index": 1, "constituents": [{"category": "NP", "index": 0, "constituents": [{"category": "DT", "index": 0, "constituents": [{"category": "the", "index": 0}]}, {"category": "NN", "index": 1, "constituents": [{"category": "clown", "index": 0}]}]}, {"category": "VP", "index": 1, "constituents": [{"category": "VBZ", "index": 0, "constituents": [{"category": "is", "index": 0}]}, {"category": "ADVP", "index": 1, "constituents": [{"category": "RB", "index": 0, "constituents": [{"category": "maybe", "index": 0}]}]}, {"category": "VP", "index": 2, "constituents": [{"category": "VBG", "index": 0, "constituents": [{"category": "throwin", "index": 0}]}]}]}]}]}]}, {"category": "''", "index": 3, "constituents": [{"category": "'", "index": 0}]}]}, {"category": ",", "index": 1, "constituents": [{"category": ",", "index": 0}]}, {"category": "S", "index": 2, "constituents": [{"category": "NP", "index": 0, "constituents": [{"category": "NN", "index": 0, "constituents": [{"category": "popcorn", "index": 0}]}]}, {"category": "PP", "index": 1, "constituents": [{"category": "TO", "index": 0, "constituents": [{"category": "to", "index": 0}]}, {"category": "NP", "index": 1, "constituents": [{"category": "DT", "index": 0, "constituents": [{"category": "the", "index": 0}]}, {"category": "NNS", "index": 1, "constituents": [{"category": "kids", "index": 0}]}]}]}]}, {"category": ".", "index": 3, "constituents": [{"category": ".", "index": 0}]}]}]}}, {"tokens": [{"index": 0, "word": "and", "character_offset_begin": 237, "character_offset_end": 240, "pos": "CC", "lemma": "and", "speaker": "PER0", "ner": "O"}, {"index": 1, "word": "there", "character_offset_begin": 241, "character_offset_end": 246, "pos": "EX", "lemma": "there", "speaker": "PER0", "ner": "O"}, {"index": 2, "word": "'s", "character_offset_begin": 246, "character_offset_end": 248, "pos": "VBZ", "lemma": "be", "speaker": "PER0", "ner": "O"}, {"index": 3, "word": "somebody", "character_offset_begin": 249, "character_offset_end": 257, "pos": "NN", "lemma": "somebody", "speaker": "PER0", "ner": "O"}, {"index": 4, "word": "on", "character_offset_begin": 258, "character_offset_end": 260, "pos": "IN", "lemma": "on", "speaker": "PER0", "ner": "O"}, {"index": 5, "word": "a", "character_offset_begin": 261, "character_offset_end": 262, "pos": "DT", "lemma": "a", "speaker": "PER0", "ner": "O"}, {"index": 6, "word": "tightrope", "character_offset_begin": 263, "character_offset_end": 272, "pos": "NN", "lemma": "tightrope", "speaker": "PER0", "ner": "O"}, {"index": 7, "word": "walking", "character_offset_begin": 273, "character_offset_end": 280, "pos": "NN", "lemma": "walking", "speaker": "PER0", "ner": "O"}, {"index": 8, "word": ".", "character_offset_begin": 280, "character_offset_end": 281, "pos": ".", "lemma": ".", "speaker": "PER0", "ner": "O"}], "index": 7, "dependencies": [{"target": {"index": 6, "begin_position": 261, "value": "a", "end_position": 262}, "dependent": {"index": 6, "begin_position": 261, "value": "a", "end_position": 262}, "is_extra": false, "governor": {"index": 8, "begin_position": 273, "value": "walking", "end_position": 280}, "source": {"index": 8, "begin_position": 273, "value": "walking", "end_position": 280}, "relation": {"description": "determiner", "value": "det"}}, {"target": {"index": 7, "begin_position": 263, "value": "tightrope", "end_position": 272}, "dependent": {"index": 7, "begin_position": 263, "value": "tightrope", "end_position": 272}, "is_extra": false, "governor": {"index": 8, "begin_position": 273, "value": "walking", "end_position": 280}, "source": {"index": 8, "begin_position": 273, "value": "walking", "end_position": 280}, "relation": {"description": "nn modifier", "value": "nn"}}, {"target": {"index": 1, "begin_position": 237, "value": "and", "end_position": 240}, "dependent": {"index": 1, "begin_position": 237, "value": "and", "end_position": 240}, "is_extra": false, "governor": {"index": 3, "begin_position": 246, "value": "'s", "end_position": 248}, "source": {"index": 3, "begin_position": 246, "value": "'s", "end_position": 248}, "relation": {"description": "coordination", "value": "cc"}}, {"target": {"index": 2, "begin_position": 241, "value": "there", "end_position": 246}, "dependent": {"index": 2, "begin_position": 241, "value": "there", "end_position": 246}, "is_extra": false, "governor": {"index": 3, "begin_position": 246, "value": "'s", "end_position": 248}, "source": {"index": 3, "begin_position": 246, "value": "'s", "end_position": 248}, "relation": {"description": "expletive", "value": "expl"}}, {"target": {"index": 4, "begin_position": 249, "value": "somebody", "end_position": 257}, "dependent": {"index": 4, "begin_position": 249, "value": "somebody", "end_position": 257}, "is_extra": false, "governor": {"index": 3, "begin_position": 246, "value": "'s", "end_position": 248}, "source": {"index": 3, "begin_position": 246, "value": "'s", "end_position": 248}, "relation": {"description": "nominal subject", "value": "nsubj"}}, {"target": {"index": 8, "begin_position": 273, "value": "walking", "end_position": 280}, "dependent": {"index": 8, "begin_position": 273, "value": "walking", "end_position": 280}, "is_extra": false, "governor": {"index": 4, "begin_position": 249, "value": "somebody", "end_position": 257}, "source": {"index": 4, "begin_position": 249, "value": "somebody", "end_position": 257}, "relation": {"description": "prep_collapsed", "value": "prep"}}], "phrase_structure": {"category": "ROOT", "constituents": [{"category": "S", "index": 0, "constituents": [{"category": "CC", "index": 0, "constituents": [{"category": "and", "index": 0}]}, {"category": "NP", "index": 1, "constituents": [{"category": "EX", "index": 0, "constituents": [{"category": "there", "index": 0}]}]}, {"category": "VP", "index": 2, "constituents": [{"category": "VBZ", "index": 0, "constituents": [{"category": "'s", "index": 0}]}, {"category": "NP", "index": 1, "constituents": [{"category": "NP", "index": 0, "constituents": [{"category": "NN", "index": 0, "constituents": [{"category": "somebody", "index": 0}]}]}, {"category": "PP", "index": 1, "constituents": [{"category": "IN", "index": 0, "constituents": [{"category": "on", "index": 0}]}, {"category": "NP", "index": 1, "constituents": [{"category": "DT", "index": 0, "constituents": [{"category": "a", "index": 0}]}, {"category": "NN", "index": 1, "constituents": [{"category": "tightrope", "index": 0}]}, {"category": "NN", "index": 2, "constituents": [{"category": "walking", "index": 0}]}]}]}]}]}, {"category": ".", "index": 3, "constituents": [{"category": ".", "index": 0}]}]}]}}, {"tokens": [{"index": 0, "word": "that", "character_offset_begin": 282, "character_offset_end": 286, "pos": "DT", "lemma": "that", "speaker": "PER0", "ner": "O"}, {"index": 1, "word": "'s", "character_offset_begin": 286, "character_offset_end": 288, "pos": "VBZ", "lemma": "be", "speaker": "PER0", "ner": "O"}, {"index": 2, "word": "it", "character_offset_begin": 289, "character_offset_end": 291, "pos": "PRP", "lemma": "it", "speaker": "PER0", "ner": "O"}, {"index": 3, "word": ".", "character_offset_begin": 291, "character_offset_end": 292, "pos": ".", "lemma": ".", "speaker": "PER0", "ner": "O"}], "index": 8, "dependencies": [{"target": {"index": 1, "begin_position": 282, "value": "that", "end_position": 286}, "dependent": {"index": 1, "begin_position": 282, "value": "that", "end_position": 286}, "is_extra": false, "governor": {"index": 3, "begin_position": 289, "value": "it", "end_position": 291}, "source": {"index": 3, "begin_position": 289, "value": "it", "end_position": 291}, "relation": {"description": "nominal subject", "value": "nsubj"}}, {"target": {"index": 2, "begin_position": 286, "value": "'s", "end_position": 288}, "dependent": {"index": 2, "begin_position": 286, "value": "'s", "end_position": 288}, "is_extra": false, "governor": {"index": 3, "begin_position": 289, "value": "it", "end_position": 291}, "source": {"index": 3, "begin_position": 289, "value": "it", "end_position": 291}, "relation": {"description": "copula", "value": "cop"}}], "phrase_structure": {"category": "ROOT", "constituents": [{"category": "S", "index": 0, "constituents": [{"category": "NP", "index": 0, "constituents": [{"category": "DT", "index": 0, "constituents": [{"category": "that", "index": 0}]}]}, {"category": "VP", "index": 1, "constituents": [{"category": "VBZ", "index": 0, "constituents": [{"category": "'s", "index": 0}]}, {"category": "NP", "index": 1, "constituents": [{"category": "PRP", "index": 0, "constituents": [{"category": "it", "index": 0}]}]}]}, {"category": ".", "index": 2, "constituents": [{"category": ".", "index": 0}]}]}]}}]}